[
  {
    "symbol": "AAPL",
    "name": "Apple Inc.",
    "enName": "Apple Inc.",
    "sector": "เทคโนโลยี",
    "market": "NASDAQ",
    "price": 100,
    "prevClose": 99,
    "sharesOutstanding": 1000,
    "color": "#2563EB",
    "about": "ข้อมูลหลักทรัพย์ AAPL - Apple Inc. จดทะเบียนในตลาด NASDAQ สหรัฐอเมริกา ดึงข้อมูลวิเคราะห์เชิงลึกสดเรียลไทม์ด้วย API",
    "revenueHistory": [],
    "fcfHistory": [],
    "priceHistory": [],
    "financials": {
      "revenue": 0,
      "netIncome": 0,
      "eps": 0,
      "bookValuePerShare": 0,
      "freeCashFlow": 0,
      "ebitda": 0,
      "totalDebt": 0,
      "cash": 0,
      "dividendPerShare": 0,
      "growthRate": 0.08
    },
    "assetType": "US_STOCK",
    "currency": "USD"
  },
  {
    "symbol": "ABNB",
    "name": "Airbnb, Inc. Class A Common Stock",
    "enName": "Airbnb, Inc. Class A Common Stock",
    "sector": "เทคโนโลยี",
    "market": "NASDAQ",
    "price": 100,
    "prevClose": 99,
    "sharesOutstanding": 1000,
    "color": "#2563EB",
    "about": "ข้อมูลหลักทรัพย์ ABNB - Airbnb, Inc. Class A Common Stock จดทะเบียนในตลาด NASDAQ สหรัฐอเมริกา ดึงข้อมูลวิเคราะห์เชิงลึกสดเรียลไทม์ด้วย API",
    "revenueHistory": [],
    "fcfHistory": [],
    "priceHistory": [],
    "financials": {
      "revenue": 0,
      "netIncome": 0,
      "eps": 0,
      "bookValuePerShare": 0,
      "freeCashFlow": 0,
      "ebitda": 0,
      "totalDebt": 0,
      "cash": 0,
      "dividendPerShare": 0,
      "growthRate": 0.08
    },
    "assetType": "US_STOCK",
    "currency": "USD"
  },
  {
    "symbol": "ADBE",
    "name": "Adobe Inc.",
    "enName": "Adobe Inc.",
    "sector": "เทคโนโลยี",
    "market": "NASDAQ",
    "price": 100,
    "prevClose": 99,
    "sharesOutstanding": 1000,
    "color": "#2563EB",
    "about": "ข้อมูลหลักทรัพย์ ADBE - Adobe Inc. จดทะเบียนในตลาด NASDAQ สหรัฐอเมริกา ดึงข้อมูลวิเคราะห์เชิงลึกสดเรียลไทม์ด้วย API",
    "revenueHistory": [],
    "fcfHistory": [],
    "priceHistory": [],
    "financials": {
      "revenue": 0,
      "netIncome": 0,
      "eps": 0,
      "bookValuePerShare": 0,
      "freeCashFlow": 0,
      "ebitda": 0,
      "totalDebt": 0,
      "cash": 0,
      "dividendPerShare": 0,
      "growthRate": 0.08
    },
    "assetType": "US_STOCK",
    "currency": "USD"
  },
  {
    "symbol": "ADP",
    "name": "Automatic Data Processing",
    "enName": "Automatic Data Processing",
    "sector": "เทคโนโลยี",
    "market": "NASDAQ",
    "price": 100,
    "prevClose": 99,
    "sharesOutstanding": 1000,
    "color": "#2563EB",
    "about": "ข้อมูลหลักทรัพย์ ADP - Automatic Data Processing จดทะเบียนในตลาด NASDAQ สหรัฐอเมริกา ดึงข้อมูลวิเคราะห์เชิงลึกสดเรียลไทม์ด้วย API",
    "revenueHistory": [],
    "fcfHistory": [],
    "priceHistory": [],
    "financials": {
      "revenue": 0,
      "netIncome": 0,
      "eps": 0,
      "bookValuePerShare": 0,
      "freeCashFlow": 0,
      "ebitda": 0,
      "totalDebt": 0,
      "cash": 0,
      "dividendPerShare": 0,
      "growthRate": 0.08
    },
    "assetType": "US_STOCK",
    "currency": "USD"
  },
  {
    "symbol": "ADSK",
    "name": "Autodesk Inc",
    "enName": "Autodesk Inc",
    "sector": "เทคโนโลยี",
    "market": "NASDAQ",
    "price": 100,
    "prevClose": 99,
    "sharesOutstanding": 1000,
    "color": "#2563EB",
    "about": "ข้อมูลหลักทรัพย์ ADSK - Autodesk Inc จดทะเบียนในตลาด NASDAQ สหรัฐอเมริกา ดึงข้อมูลวิเคราะห์เชิงลึกสดเรียลไทม์ด้วย API",
    "revenueHistory": [],
    "fcfHistory": [],
    "priceHistory": [],
    "financials": {
      "revenue": 0,
      "netIncome": 0,
      "eps": 0,
      "bookValuePerShare": 0,
      "freeCashFlow": 0,
      "ebitda": 0,
      "totalDebt": 0,
      "cash": 0,
      "dividendPerShare": 0,
      "growthRate": 0.08
    },
    "assetType": "US_STOCK",
    "currency": "USD"
  },
  {
    "symbol": "AEP",
    "name": "American Electric Power Company, Inc.",
    "enName": "American Electric Power Company, Inc.",
    "sector": "พลังงาน",
    "market": "NASDAQ",
    "price": 100,
    "prevClose": 99,
    "sharesOutstanding": 1000,
    "color": "#2563EB",
    "about": "ข้อมูลหลักทรัพย์ AEP - American Electric Power Company, Inc. จดทะเบียนในตลาด NASDAQ สหรัฐอเมริกา ดึงข้อมูลวิเคราะห์เชิงลึกสดเรียลไทม์ด้วย API",
    "revenueHistory": [],
    "fcfHistory": [],
    "priceHistory": [],
    "financials": {
      "revenue": 0,
      "netIncome": 0,
      "eps": 0,
      "bookValuePerShare": 0,
      "freeCashFlow": 0,
      "ebitda": 0,
      "totalDebt": 0,
      "cash": 0,
      "dividendPerShare": 0,
      "growthRate": 0.08
    },
    "assetType": "US_STOCK",
    "currency": "USD"
  },
  {
    "symbol": "ALGN",
    "name": "Align Technology Inc",
    "enName": "Align Technology Inc",
    "sector": "เทคโนโลยี",
    "market": "NASDAQ",
    "price": 100,
    "prevClose": 99,
    "sharesOutstanding": 1000,
    "color": "#2563EB",
    "about": "ข้อมูลหลักทรัพย์ ALGN - Align Technology Inc จดทะเบียนในตลาด NASDAQ สหรัฐอเมริกา ดึงข้อมูลวิเคราะห์เชิงลึกสดเรียลไทม์ด้วย API",
    "revenueHistory": [],
    "fcfHistory": [],
    "priceHistory": [],
    "financials": {
      "revenue": 0,
      "netIncome": 0,
      "eps": 0,
      "bookValuePerShare": 0,
      "freeCashFlow": 0,
      "ebitda": 0,
      "totalDebt": 0,
      "cash": 0,
      "dividendPerShare": 0,
      "growthRate": 0.08
    },
    "assetType": "US_STOCK",
    "currency": "USD"
  },
  {
    "symbol": "AMAT",
    "name": "Applied Materials Inc",
    "enName": "Applied Materials Inc",
    "sector": "เทคโนโลยี",
    "market": "NASDAQ",
    "price": 100,
    "prevClose": 99,
    "sharesOutstanding": 1000,
    "color": "#2563EB",
    "about": "ข้อมูลหลักทรัพย์ AMAT - Applied Materials Inc จดทะเบียนในตลาด NASDAQ สหรัฐอเมริกา ดึงข้อมูลวิเคราะห์เชิงลึกสดเรียลไทม์ด้วย API",
    "revenueHistory": [],
    "fcfHistory": [],
    "priceHistory": [],
    "financials": {
      "revenue": 0,
      "netIncome": 0,
      "eps": 0,
      "bookValuePerShare": 0,
      "freeCashFlow": 0,
      "ebitda": 0,
      "totalDebt": 0,
      "cash": 0,
      "dividendPerShare": 0,
      "growthRate": 0.08
    },
    "assetType": "US_STOCK",
    "currency": "USD"
  },
  {
    "symbol": "AMD",
    "name": "Advanced Micro Devices",
    "enName": "Advanced Micro Devices",
    "sector": "เทคโนโลยี",
    "market": "NASDAQ",
    "price": 100,
    "prevClose": 99,
    "sharesOutstanding": 1000,
    "color": "#2563EB",
    "about": "ข้อมูลหลักทรัพย์ AMD - Advanced Micro Devices จดทะเบียนในตลาด NASDAQ สหรัฐอเมริกา ดึงข้อมูลวิเคราะห์เชิงลึกสดเรียลไทม์ด้วย API",
    "revenueHistory": [],
    "fcfHistory": [],
    "priceHistory": [],
    "financials": {
      "revenue": 0,
      "netIncome": 0,
      "eps": 0,
      "bookValuePerShare": 0,
      "freeCashFlow": 0,
      "ebitda": 0,
      "totalDebt": 0,
      "cash": 0,
      "dividendPerShare": 0,
      "growthRate": 0.08
    },
    "assetType": "US_STOCK",
    "currency": "USD"
  },
  {
    "symbol": "AMGN",
    "name": "Amgen Inc",
    "enName": "Amgen Inc",
    "sector": "เทคโนโลยี",
    "market": "NASDAQ",
    "price": 100,
    "prevClose": 99,
    "sharesOutstanding": 1000,
    "color": "#2563EB",
    "about": "ข้อมูลหลักทรัพย์ AMGN - Amgen Inc จดทะเบียนในตลาด NASDAQ สหรัฐอเมริกา ดึงข้อมูลวิเคราะห์เชิงลึกสดเรียลไทม์ด้วย API",
    "revenueHistory": [],
    "fcfHistory": [],
    "priceHistory": [],
    "financials": {
      "revenue": 0,
      "netIncome": 0,
      "eps": 0,
      "bookValuePerShare": 0,
      "freeCashFlow": 0,
      "ebitda": 0,
      "totalDebt": 0,
      "cash": 0,
      "dividendPerShare": 0,
      "growthRate": 0.08
    },
    "assetType": "US_STOCK",
    "currency": "USD"
  },
  {
    "symbol": "AMZN",
    "name": "Amazon.Com Inc",
    "enName": "Amazon.Com Inc",
    "sector": "เทคโนโลยี",
    "market": "NASDAQ",
    "price": 100,
    "prevClose": 99,
    "sharesOutstanding": 1000,
    "color": "#2563EB",
    "about": "ข้อมูลหลักทรัพย์ AMZN - Amazon.Com Inc จดทะเบียนในตลาด NASDAQ สหรัฐอเมริกา ดึงข้อมูลวิเคราะห์เชิงลึกสดเรียลไทม์ด้วย API",
    "revenueHistory": [],
    "fcfHistory": [],
    "priceHistory": [],
    "financials": {
      "revenue": 0,
      "netIncome": 0,
      "eps": 0,
      "bookValuePerShare": 0,
      "freeCashFlow": 0,
      "ebitda": 0,
      "totalDebt": 0,
      "cash": 0,
      "dividendPerShare": 0,
      "growthRate": 0.08
    },
    "assetType": "US_STOCK",
    "currency": "USD"
  },
  {
    "symbol": "ASML",
    "name": "ASML Holding NV",
    "enName": "ASML Holding NV",
    "sector": "เทคโนโลยี",
    "market": "NASDAQ",
    "price": 100,
    "prevClose": 99,
    "sharesOutstanding": 1000,
    "color": "#2563EB",
    "about": "ข้อมูลหลักทรัพย์ ASML - ASML Holding NV จดทะเบียนในตลาด NASDAQ สหรัฐอเมริกา ดึงข้อมูลวิเคราะห์เชิงลึกสดเรียลไทม์ด้วย API",
    "revenueHistory": [],
    "fcfHistory": [],
    "priceHistory": [],
    "financials": {
      "revenue": 0,
      "netIncome": 0,
      "eps": 0,
      "bookValuePerShare": 0,
      "freeCashFlow": 0,
      "ebitda": 0,
      "totalDebt": 0,
      "cash": 0,
      "dividendPerShare": 0,
      "growthRate": 0.08
    },
    "assetType": "US_STOCK",
    "currency": "USD"
  },
  {
    "symbol": "AVGO",
    "name": "Broadcom Inc. Common Stock",
    "enName": "Broadcom Inc. Common Stock",
    "sector": "เทคโนโลยี",
    "market": "NASDAQ",
    "price": 100,
    "prevClose": 99,
    "sharesOutstanding": 1000,
    "color": "#2563EB",
    "about": "ข้อมูลหลักทรัพย์ AVGO - Broadcom Inc. Common Stock จดทะเบียนในตลาด NASDAQ สหรัฐอเมริกา ดึงข้อมูลวิเคราะห์เชิงลึกสดเรียลไทม์ด้วย API",
    "revenueHistory": [],
    "fcfHistory": [],
    "priceHistory": [],
    "financials": {
      "revenue": 0,
      "netIncome": 0,
      "eps": 0,
      "bookValuePerShare": 0,
      "freeCashFlow": 0,
      "ebitda": 0,
      "totalDebt": 0,
      "cash": 0,
      "dividendPerShare": 0,
      "growthRate": 0.08
    },
    "assetType": "US_STOCK",
    "currency": "USD"
  },
  {
    "symbol": "BIDU",
    "name": "Baidu, Inc.",
    "enName": "Baidu, Inc.",
    "sector": "เทคโนโลยี",
    "market": "NASDAQ",
    "price": 100,
    "prevClose": 99,
    "sharesOutstanding": 1000,
    "color": "#2563EB",
    "about": "ข้อมูลหลักทรัพย์ BIDU - Baidu, Inc. จดทะเบียนในตลาด NASDAQ สหรัฐอเมริกา ดึงข้อมูลวิเคราะห์เชิงลึกสดเรียลไทม์ด้วย API",
    "revenueHistory": [],
    "fcfHistory": [],
    "priceHistory": [],
    "financials": {
      "revenue": 0,
      "netIncome": 0,
      "eps": 0,
      "bookValuePerShare": 0,
      "freeCashFlow": 0,
      "ebitda": 0,
      "totalDebt": 0,
      "cash": 0,
      "dividendPerShare": 0,
      "growthRate": 0.08
    },
    "assetType": "US_STOCK",
    "currency": "USD"
  },
  {
    "symbol": "BIIB",
    "name": "Biogen Inc. Common Stock",
    "enName": "Biogen Inc. Common Stock",
    "sector": "เทคโนโลยี",
    "market": "NASDAQ",
    "price": 100,
    "prevClose": 99,
    "sharesOutstanding": 1000,
    "color": "#2563EB",
    "about": "ข้อมูลหลักทรัพย์ BIIB - Biogen Inc. Common Stock จดทะเบียนในตลาด NASDAQ สหรัฐอเมริกา ดึงข้อมูลวิเคราะห์เชิงลึกสดเรียลไทม์ด้วย API",
    "revenueHistory": [],
    "fcfHistory": [],
    "priceHistory": [],
    "financials": {
      "revenue": 0,
      "netIncome": 0,
      "eps": 0,
      "bookValuePerShare": 0,
      "freeCashFlow": 0,
      "ebitda": 0,
      "totalDebt": 0,
      "cash": 0,
      "dividendPerShare": 0,
      "growthRate": 0.08
    },
    "assetType": "US_STOCK",
    "currency": "USD"
  },
  {
    "symbol": "BILI",
    "name": "Bilibili Inc. American Depositary Shares",
    "enName": "Bilibili Inc. American Depositary Shares",
    "sector": "เทคโนโลยี",
    "market": "NASDAQ",
    "price": 100,
    "prevClose": 99,
    "sharesOutstanding": 1000,
    "color": "#2563EB",
    "about": "ข้อมูลหลักทรัพย์ BILI - Bilibili Inc. American Depositary Shares จดทะเบียนในตลาด NASDAQ สหรัฐอเมริกา ดึงข้อมูลวิเคราะห์เชิงลึกสดเรียลไทม์ด้วย API",
    "revenueHistory": [],
    "fcfHistory": [],
    "priceHistory": [],
    "financials": {
      "revenue": 0,
      "netIncome": 0,
      "eps": 0,
      "bookValuePerShare": 0,
      "freeCashFlow": 0,
      "ebitda": 0,
      "totalDebt": 0,
      "cash": 0,
      "dividendPerShare": 0,
      "growthRate": 0.08
    },
    "assetType": "US_STOCK",
    "currency": "USD"
  },
  {
    "symbol": "BKNG",
    "name": "Booking Holdings Inc. Common Stock",
    "enName": "Booking Holdings Inc. Common Stock",
    "sector": "ธนาคาร",
    "market": "NASDAQ",
    "price": 100,
    "prevClose": 99,
    "sharesOutstanding": 1000,
    "color": "#2563EB",
    "about": "ข้อมูลหลักทรัพย์ BKNG - Booking Holdings Inc. Common Stock จดทะเบียนในตลาด NASDAQ สหรัฐอเมริกา ดึงข้อมูลวิเคราะห์เชิงลึกสดเรียลไทม์ด้วย API",
    "revenueHistory": [],
    "fcfHistory": [],
    "priceHistory": [],
    "financials": {
      "revenue": 0,
      "netIncome": 0,
      "eps": 0,
      "bookValuePerShare": 0,
      "freeCashFlow": 0,
      "ebitda": 0,
      "totalDebt": 0,
      "cash": 0,
      "dividendPerShare": 0,
      "growthRate": 0.08
    },
    "assetType": "US_STOCK",
    "currency": "USD"
  },
  {
    "symbol": "BKR",
    "name": "Baker Hughes Company",
    "enName": "Baker Hughes Company",
    "sector": "เทคโนโลยี",
    "market": "NASDAQ",
    "price": 100,
    "prevClose": 99,
    "sharesOutstanding": 1000,
    "color": "#2563EB",
    "about": "ข้อมูลหลักทรัพย์ BKR - Baker Hughes Company จดทะเบียนในตลาด NASDAQ สหรัฐอเมริกา ดึงข้อมูลวิเคราะห์เชิงลึกสดเรียลไทม์ด้วย API",
    "revenueHistory": [],
    "fcfHistory": [],
    "priceHistory": [],
    "financials": {
      "revenue": 0,
      "netIncome": 0,
      "eps": 0,
      "bookValuePerShare": 0,
      "freeCashFlow": 0,
      "ebitda": 0,
      "totalDebt": 0,
      "cash": 0,
      "dividendPerShare": 0,
      "growthRate": 0.08
    },
    "assetType": "US_STOCK",
    "currency": "USD"
  },
  {
    "symbol": "BYND",
    "name": "Beyond Meat, Inc. Common Stock",
    "enName": "Beyond Meat, Inc. Common Stock",
    "sector": "เทคโนโลยี",
    "market": "NASDAQ",
    "price": 100,
    "prevClose": 99,
    "sharesOutstanding": 1000,
    "color": "#2563EB",
    "about": "ข้อมูลหลักทรัพย์ BYND - Beyond Meat, Inc. Common Stock จดทะเบียนในตลาด NASDAQ สหรัฐอเมริกา ดึงข้อมูลวิเคราะห์เชิงลึกสดเรียลไทม์ด้วย API",
    "revenueHistory": [],
    "fcfHistory": [],
    "priceHistory": [],
    "financials": {
      "revenue": 0,
      "netIncome": 0,
      "eps": 0,
      "bookValuePerShare": 0,
      "freeCashFlow": 0,
      "ebitda": 0,
      "totalDebt": 0,
      "cash": 0,
      "dividendPerShare": 0,
      "growthRate": 0.08
    },
    "assetType": "US_STOCK",
    "currency": "USD"
  },
  {
    "symbol": "CDNS",
    "name": "Cadence Design Systems",
    "enName": "Cadence Design Systems",
    "sector": "เทคโนโลยี",
    "market": "NASDAQ",
    "price": 100,
    "prevClose": 99,
    "sharesOutstanding": 1000,
    "color": "#2563EB",
    "about": "ข้อมูลหลักทรัพย์ CDNS - Cadence Design Systems จดทะเบียนในตลาด NASDAQ สหรัฐอเมริกา ดึงข้อมูลวิเคราะห์เชิงลึกสดเรียลไทม์ด้วย API",
    "revenueHistory": [],
    "fcfHistory": [],
    "priceHistory": [],
    "financials": {
      "revenue": 0,
      "netIncome": 0,
      "eps": 0,
      "bookValuePerShare": 0,
      "freeCashFlow": 0,
      "ebitda": 0,
      "totalDebt": 0,
      "cash": 0,
      "dividendPerShare": 0,
      "growthRate": 0.08
    },
    "assetType": "US_STOCK",
    "currency": "USD"
  },
  {
    "symbol": "COIN",
    "name": "Coinbase Global, Inc. Class A Common Stock",
    "enName": "Coinbase Global, Inc. Class A Common Stock",
    "sector": "เทคโนโลยี",
    "market": "NASDAQ",
    "price": 100,
    "prevClose": 99,
    "sharesOutstanding": 1000,
    "color": "#2563EB",
    "about": "ข้อมูลหลักทรัพย์ COIN - Coinbase Global, Inc. Class A Common Stock จดทะเบียนในตลาด NASDAQ สหรัฐอเมริกา ดึงข้อมูลวิเคราะห์เชิงลึกสดเรียลไทม์ด้วย API",
    "revenueHistory": [],
    "fcfHistory": [],
    "priceHistory": [],
    "financials": {
      "revenue": 0,
      "netIncome": 0,
      "eps": 0,
      "bookValuePerShare": 0,
      "freeCashFlow": 0,
      "ebitda": 0,
      "totalDebt": 0,
      "cash": 0,
      "dividendPerShare": 0,
      "growthRate": 0.08
    },
    "assetType": "US_STOCK",
    "currency": "USD"
  },
  {
    "symbol": "COST",
    "name": "Costco Wholesale Corp",
    "enName": "Costco Wholesale Corp",
    "sector": "เทคโนโลยี",
    "market": "NASDAQ",
    "price": 100,
    "prevClose": 99,
    "sharesOutstanding": 1000,
    "color": "#2563EB",
    "about": "ข้อมูลหลักทรัพย์ COST - Costco Wholesale Corp จดทะเบียนในตลาด NASDAQ สหรัฐอเมริกา ดึงข้อมูลวิเคราะห์เชิงลึกสดเรียลไทม์ด้วย API",
    "revenueHistory": [],
    "fcfHistory": [],
    "priceHistory": [],
    "financials": {
      "revenue": 0,
      "netIncome": 0,
      "eps": 0,
      "bookValuePerShare": 0,
      "freeCashFlow": 0,
      "ebitda": 0,
      "totalDebt": 0,
      "cash": 0,
      "dividendPerShare": 0,
      "growthRate": 0.08
    },
    "assetType": "US_STOCK",
    "currency": "USD"
  },
  {
    "symbol": "CPRT",
    "name": "Copart Inc",
    "enName": "Copart Inc",
    "sector": "เทคโนโลยี",
    "market": "NASDAQ",
    "price": 100,
    "prevClose": 99,
    "sharesOutstanding": 1000,
    "color": "#2563EB",
    "about": "ข้อมูลหลักทรัพย์ CPRT - Copart Inc จดทะเบียนในตลาด NASDAQ สหรัฐอเมริกา ดึงข้อมูลวิเคราะห์เชิงลึกสดเรียลไทม์ด้วย API",
    "revenueHistory": [],
    "fcfHistory": [],
    "priceHistory": [],
    "financials": {
      "revenue": 0,
      "netIncome": 0,
      "eps": 0,
      "bookValuePerShare": 0,
      "freeCashFlow": 0,
      "ebitda": 0,
      "totalDebt": 0,
      "cash": 0,
      "dividendPerShare": 0,
      "growthRate": 0.08
    },
    "assetType": "US_STOCK",
    "currency": "USD"
  },
  {
    "symbol": "CRWD",
    "name": "CrowdStrike Holdings, Inc. Class A Common Stock",
    "enName": "CrowdStrike Holdings, Inc. Class A Common Stock",
    "sector": "ธนาคาร",
    "market": "NASDAQ",
    "price": 100,
    "prevClose": 99,
    "sharesOutstanding": 1000,
    "color": "#2563EB",
    "about": "ข้อมูลหลักทรัพย์ CRWD - CrowdStrike Holdings, Inc. Class A Common Stock จดทะเบียนในตลาด NASDAQ สหรัฐอเมริกา ดึงข้อมูลวิเคราะห์เชิงลึกสดเรียลไทม์ด้วย API",
    "revenueHistory": [],
    "fcfHistory": [],
    "priceHistory": [],
    "financials": {
      "revenue": 0,
      "netIncome": 0,
      "eps": 0,
      "bookValuePerShare": 0,
      "freeCashFlow": 0,
      "ebitda": 0,
      "totalDebt": 0,
      "cash": 0,
      "dividendPerShare": 0,
      "growthRate": 0.08
    },
    "assetType": "US_STOCK",
    "currency": "USD"
  },
  {
    "symbol": "CSCO",
    "name": "Cisco Systems, Inc. Common Stock (DE)",
    "enName": "Cisco Systems, Inc. Common Stock (DE)",
    "sector": "เทคโนโลยี",
    "market": "NASDAQ",
    "price": 100,
    "prevClose": 99,
    "sharesOutstanding": 1000,
    "color": "#2563EB",
    "about": "ข้อมูลหลักทรัพย์ CSCO - Cisco Systems, Inc. Common Stock (DE) จดทะเบียนในตลาด NASDAQ สหรัฐอเมริกา ดึงข้อมูลวิเคราะห์เชิงลึกสดเรียลไทม์ด้วย API",
    "revenueHistory": [],
    "fcfHistory": [],
    "priceHistory": [],
    "financials": {
      "revenue": 0,
      "netIncome": 0,
      "eps": 0,
      "bookValuePerShare": 0,
      "freeCashFlow": 0,
      "ebitda": 0,
      "totalDebt": 0,
      "cash": 0,
      "dividendPerShare": 0,
      "growthRate": 0.08
    },
    "assetType": "US_STOCK",
    "currency": "USD"
  },
  {
    "symbol": "CSX",
    "name": "CSX Corporation",
    "enName": "CSX Corporation",
    "sector": "เทคโนโลยี",
    "market": "NASDAQ",
    "price": 100,
    "prevClose": 99,
    "sharesOutstanding": 1000,
    "color": "#2563EB",
    "about": "ข้อมูลหลักทรัพย์ CSX - CSX Corporation จดทะเบียนในตลาด NASDAQ สหรัฐอเมริกา ดึงข้อมูลวิเคราะห์เชิงลึกสดเรียลไทม์ด้วย API",
    "revenueHistory": [],
    "fcfHistory": [],
    "priceHistory": [],
    "financials": {
      "revenue": 0,
      "netIncome": 0,
      "eps": 0,
      "bookValuePerShare": 0,
      "freeCashFlow": 0,
      "ebitda": 0,
      "totalDebt": 0,
      "cash": 0,
      "dividendPerShare": 0,
      "growthRate": 0.08
    },
    "assetType": "US_STOCK",
    "currency": "USD"
  },
  {
    "symbol": "DDOG",
    "name": "Datadog, Inc. Class A Common Stock",
    "enName": "Datadog, Inc. Class A Common Stock",
    "sector": "เทคโนโลยี",
    "market": "NASDAQ",
    "price": 100,
    "prevClose": 99,
    "sharesOutstanding": 1000,
    "color": "#2563EB",
    "about": "ข้อมูลหลักทรัพย์ DDOG - Datadog, Inc. Class A Common Stock จดทะเบียนในตลาด NASDAQ สหรัฐอเมริกา ดึงข้อมูลวิเคราะห์เชิงลึกสดเรียลไทม์ด้วย API",
    "revenueHistory": [],
    "fcfHistory": [],
    "priceHistory": [],
    "financials": {
      "revenue": 0,
      "netIncome": 0,
      "eps": 0,
      "bookValuePerShare": 0,
      "freeCashFlow": 0,
      "ebitda": 0,
      "totalDebt": 0,
      "cash": 0,
      "dividendPerShare": 0,
      "growthRate": 0.08
    },
    "assetType": "US_STOCK",
    "currency": "USD"
  },
  {
    "symbol": "DLTR",
    "name": "Dollar Tree Inc.",
    "enName": "Dollar Tree Inc.",
    "sector": "เทคโนโลยี",
    "market": "NASDAQ",
    "price": 100,
    "prevClose": 99,
    "sharesOutstanding": 1000,
    "color": "#2563EB",
    "about": "ข้อมูลหลักทรัพย์ DLTR - Dollar Tree Inc. จดทะเบียนในตลาด NASDAQ สหรัฐอเมริกา ดึงข้อมูลวิเคราะห์เชิงลึกสดเรียลไทม์ด้วย API",
    "revenueHistory": [],
    "fcfHistory": [],
    "priceHistory": [],
    "financials": {
      "revenue": 0,
      "netIncome": 0,
      "eps": 0,
      "bookValuePerShare": 0,
      "freeCashFlow": 0,
      "ebitda": 0,
      "totalDebt": 0,
      "cash": 0,
      "dividendPerShare": 0,
      "growthRate": 0.08
    },
    "assetType": "US_STOCK",
    "currency": "USD"
  },
  {
    "symbol": "DOCU",
    "name": "DocuSign, Inc. Common Stock",
    "enName": "DocuSign, Inc. Common Stock",
    "sector": "เทคโนโลยี",
    "market": "NASDAQ",
    "price": 100,
    "prevClose": 99,
    "sharesOutstanding": 1000,
    "color": "#2563EB",
    "about": "ข้อมูลหลักทรัพย์ DOCU - DocuSign, Inc. Common Stock จดทะเบียนในตลาด NASDAQ สหรัฐอเมริกา ดึงข้อมูลวิเคราะห์เชิงลึกสดเรียลไทม์ด้วย API",
    "revenueHistory": [],
    "fcfHistory": [],
    "priceHistory": [],
    "financials": {
      "revenue": 0,
      "netIncome": 0,
      "eps": 0,
      "bookValuePerShare": 0,
      "freeCashFlow": 0,
      "ebitda": 0,
      "totalDebt": 0,
      "cash": 0,
      "dividendPerShare": 0,
      "growthRate": 0.08
    },
    "assetType": "US_STOCK",
    "currency": "USD"
  },
  {
    "symbol": "EBAY",
    "name": "eBay Inc",
    "enName": "eBay Inc",
    "sector": "เทคโนโลยี",
    "market": "NASDAQ",
    "price": 100,
    "prevClose": 99,
    "sharesOutstanding": 1000,
    "color": "#2563EB",
    "about": "ข้อมูลหลักทรัพย์ EBAY - eBay Inc จดทะเบียนในตลาด NASDAQ สหรัฐอเมริกา ดึงข้อมูลวิเคราะห์เชิงลึกสดเรียลไทม์ด้วย API",
    "revenueHistory": [],
    "fcfHistory": [],
    "priceHistory": [],
    "financials": {
      "revenue": 0,
      "netIncome": 0,
      "eps": 0,
      "bookValuePerShare": 0,
      "freeCashFlow": 0,
      "ebitda": 0,
      "totalDebt": 0,
      "cash": 0,
      "dividendPerShare": 0,
      "growthRate": 0.08
    },
    "assetType": "US_STOCK",
    "currency": "USD"
  },
  {
    "symbol": "ENPH",
    "name": "Enphase Energy, Inc.",
    "enName": "Enphase Energy, Inc.",
    "sector": "พลังงาน",
    "market": "NASDAQ",
    "price": 100,
    "prevClose": 99,
    "sharesOutstanding": 1000,
    "color": "#2563EB",
    "about": "ข้อมูลหลักทรัพย์ ENPH - Enphase Energy, Inc. จดทะเบียนในตลาด NASDAQ สหรัฐอเมริกา ดึงข้อมูลวิเคราะห์เชิงลึกสดเรียลไทม์ด้วย API",
    "revenueHistory": [],
    "fcfHistory": [],
    "priceHistory": [],
    "financials": {
      "revenue": 0,
      "netIncome": 0,
      "eps": 0,
      "bookValuePerShare": 0,
      "freeCashFlow": 0,
      "ebitda": 0,
      "totalDebt": 0,
      "cash": 0,
      "dividendPerShare": 0,
      "growthRate": 0.08
    },
    "assetType": "US_STOCK",
    "currency": "USD"
  },
  {
    "symbol": "EXC",
    "name": "Exelon Corporation",
    "enName": "Exelon Corporation",
    "sector": "เทคโนโลยี",
    "market": "NASDAQ",
    "price": 100,
    "prevClose": 99,
    "sharesOutstanding": 1000,
    "color": "#2563EB",
    "about": "ข้อมูลหลักทรัพย์ EXC - Exelon Corporation จดทะเบียนในตลาด NASDAQ สหรัฐอเมริกา ดึงข้อมูลวิเคราะห์เชิงลึกสดเรียลไทม์ด้วย API",
    "revenueHistory": [],
    "fcfHistory": [],
    "priceHistory": [],
    "financials": {
      "revenue": 0,
      "netIncome": 0,
      "eps": 0,
      "bookValuePerShare": 0,
      "freeCashFlow": 0,
      "ebitda": 0,
      "totalDebt": 0,
      "cash": 0,
      "dividendPerShare": 0,
      "growthRate": 0.08
    },
    "assetType": "US_STOCK",
    "currency": "USD"
  },
  {
    "symbol": "EXPE",
    "name": "Expedia Group, Inc. Common Stock",
    "enName": "Expedia Group, Inc. Common Stock",
    "sector": "เทคโนโลยี",
    "market": "NASDAQ",
    "price": 100,
    "prevClose": 99,
    "sharesOutstanding": 1000,
    "color": "#2563EB",
    "about": "ข้อมูลหลักทรัพย์ EXPE - Expedia Group, Inc. Common Stock จดทะเบียนในตลาด NASDAQ สหรัฐอเมริกา ดึงข้อมูลวิเคราะห์เชิงลึกสดเรียลไทม์ด้วย API",
    "revenueHistory": [],
    "fcfHistory": [],
    "priceHistory": [],
    "financials": {
      "revenue": 0,
      "netIncome": 0,
      "eps": 0,
      "bookValuePerShare": 0,
      "freeCashFlow": 0,
      "ebitda": 0,
      "totalDebt": 0,
      "cash": 0,
      "dividendPerShare": 0,
      "growthRate": 0.08
    },
    "assetType": "US_STOCK",
    "currency": "USD"
  },
  {
    "symbol": "FAST",
    "name": "Fastenal Co",
    "enName": "Fastenal Co",
    "sector": "เทคโนโลยี",
    "market": "NASDAQ",
    "price": 100,
    "prevClose": 99,
    "sharesOutstanding": 1000,
    "color": "#2563EB",
    "about": "ข้อมูลหลักทรัพย์ FAST - Fastenal Co จดทะเบียนในตลาด NASDAQ สหรัฐอเมริกา ดึงข้อมูลวิเคราะห์เชิงลึกสดเรียลไทม์ด้วย API",
    "revenueHistory": [],
    "fcfHistory": [],
    "priceHistory": [],
    "financials": {
      "revenue": 0,
      "netIncome": 0,
      "eps": 0,
      "bookValuePerShare": 0,
      "freeCashFlow": 0,
      "ebitda": 0,
      "totalDebt": 0,
      "cash": 0,
      "dividendPerShare": 0,
      "growthRate": 0.08
    },
    "assetType": "US_STOCK",
    "currency": "USD"
  },
  {
    "symbol": "FSLR",
    "name": "First Solar, Inc.",
    "enName": "First Solar, Inc.",
    "sector": "พลังงาน",
    "market": "NASDAQ",
    "price": 100,
    "prevClose": 99,
    "sharesOutstanding": 1000,
    "color": "#2563EB",
    "about": "ข้อมูลหลักทรัพย์ FSLR - First Solar, Inc. จดทะเบียนในตลาด NASDAQ สหรัฐอเมริกา ดึงข้อมูลวิเคราะห์เชิงลึกสดเรียลไทม์ด้วย API",
    "revenueHistory": [],
    "fcfHistory": [],
    "priceHistory": [],
    "financials": {
      "revenue": 0,
      "netIncome": 0,
      "eps": 0,
      "bookValuePerShare": 0,
      "freeCashFlow": 0,
      "ebitda": 0,
      "totalDebt": 0,
      "cash": 0,
      "dividendPerShare": 0,
      "growthRate": 0.08
    },
    "assetType": "US_STOCK",
    "currency": "USD"
  },
  {
    "symbol": "FTNT",
    "name": "Fortinet, Inc.",
    "enName": "Fortinet, Inc.",
    "sector": "เทคโนโลยี",
    "market": "NASDAQ",
    "price": 100,
    "prevClose": 99,
    "sharesOutstanding": 1000,
    "color": "#2563EB",
    "about": "ข้อมูลหลักทรัพย์ FTNT - Fortinet, Inc. จดทะเบียนในตลาด NASDAQ สหรัฐอเมริกา ดึงข้อมูลวิเคราะห์เชิงลึกสดเรียลไทม์ด้วย API",
    "revenueHistory": [],
    "fcfHistory": [],
    "priceHistory": [],
    "financials": {
      "revenue": 0,
      "netIncome": 0,
      "eps": 0,
      "bookValuePerShare": 0,
      "freeCashFlow": 0,
      "ebitda": 0,
      "totalDebt": 0,
      "cash": 0,
      "dividendPerShare": 0,
      "growthRate": 0.08
    },
    "assetType": "US_STOCK",
    "currency": "USD"
  },
  {
    "symbol": "GEHC",
    "name": "GE HealthCare Technologies Inc. Common Stock",
    "enName": "GE HealthCare Technologies Inc. Common Stock",
    "sector": "เทคโนโลยี",
    "market": "NASDAQ",
    "price": 100,
    "prevClose": 99,
    "sharesOutstanding": 1000,
    "color": "#2563EB",
    "about": "ข้อมูลหลักทรัพย์ GEHC - GE HealthCare Technologies Inc. Common Stock จดทะเบียนในตลาด NASDAQ สหรัฐอเมริกา ดึงข้อมูลวิเคราะห์เชิงลึกสดเรียลไทม์ด้วย API",
    "revenueHistory": [],
    "fcfHistory": [],
    "priceHistory": [],
    "financials": {
      "revenue": 0,
      "netIncome": 0,
      "eps": 0,
      "bookValuePerShare": 0,
      "freeCashFlow": 0,
      "ebitda": 0,
      "totalDebt": 0,
      "cash": 0,
      "dividendPerShare": 0,
      "growthRate": 0.08
    },
    "assetType": "US_STOCK",
    "currency": "USD"
  },
  {
    "symbol": "GILD",
    "name": "Gilead Sciences Inc",
    "enName": "Gilead Sciences Inc",
    "sector": "การแพทย์",
    "market": "NASDAQ",
    "price": 100,
    "prevClose": 99,
    "sharesOutstanding": 1000,
    "color": "#2563EB",
    "about": "ข้อมูลหลักทรัพย์ GILD - Gilead Sciences Inc จดทะเบียนในตลาด NASDAQ สหรัฐอเมริกา ดึงข้อมูลวิเคราะห์เชิงลึกสดเรียลไทม์ด้วย API",
    "revenueHistory": [],
    "fcfHistory": [],
    "priceHistory": [],
    "financials": {
      "revenue": 0,
      "netIncome": 0,
      "eps": 0,
      "bookValuePerShare": 0,
      "freeCashFlow": 0,
      "ebitda": 0,
      "totalDebt": 0,
      "cash": 0,
      "dividendPerShare": 0,
      "growthRate": 0.08
    },
    "assetType": "US_STOCK",
    "currency": "USD"
  },
  {
    "symbol": "GOOG",
    "name": "Alphabet Inc. Class C Capital Stock",
    "enName": "Alphabet Inc. Class C Capital Stock",
    "sector": "ธนาคาร",
    "market": "NASDAQ",
    "price": 100,
    "prevClose": 99,
    "sharesOutstanding": 1000,
    "color": "#2563EB",
    "about": "ข้อมูลหลักทรัพย์ GOOG - Alphabet Inc. Class C Capital Stock จดทะเบียนในตลาด NASDAQ สหรัฐอเมริกา ดึงข้อมูลวิเคราะห์เชิงลึกสดเรียลไทม์ด้วย API",
    "revenueHistory": [],
    "fcfHistory": [],
    "priceHistory": [],
    "financials": {
      "revenue": 0,
      "netIncome": 0,
      "eps": 0,
      "bookValuePerShare": 0,
      "freeCashFlow": 0,
      "ebitda": 0,
      "totalDebt": 0,
      "cash": 0,
      "dividendPerShare": 0,
      "growthRate": 0.08
    },
    "assetType": "US_STOCK",
    "currency": "USD"
  },
  {
    "symbol": "GOOGL",
    "name": "Alphabet Inc. Class A Common Stock",
    "enName": "Alphabet Inc. Class A Common Stock",
    "sector": "เทคโนโลยี",
    "market": "NASDAQ",
    "price": 100,
    "prevClose": 99,
    "sharesOutstanding": 1000,
    "color": "#2563EB",
    "about": "ข้อมูลหลักทรัพย์ GOOGL - Alphabet Inc. Class A Common Stock จดทะเบียนในตลาด NASDAQ สหรัฐอเมริกา ดึงข้อมูลวิเคราะห์เชิงลึกสดเรียลไทม์ด้วย API",
    "revenueHistory": [],
    "fcfHistory": [],
    "priceHistory": [],
    "financials": {
      "revenue": 0,
      "netIncome": 0,
      "eps": 0,
      "bookValuePerShare": 0,
      "freeCashFlow": 0,
      "ebitda": 0,
      "totalDebt": 0,
      "cash": 0,
      "dividendPerShare": 0,
      "growthRate": 0.08
    },
    "assetType": "US_STOCK",
    "currency": "USD"
  },
  {
    "symbol": "HON",
    "name": "Honeywell International, Inc.",
    "enName": "Honeywell International, Inc.",
    "sector": "เทคโนโลยี",
    "market": "NASDAQ",
    "price": 100,
    "prevClose": 99,
    "sharesOutstanding": 1000,
    "color": "#2563EB",
    "about": "ข้อมูลหลักทรัพย์ HON - Honeywell International, Inc. จดทะเบียนในตลาด NASDAQ สหรัฐอเมริกา ดึงข้อมูลวิเคราะห์เชิงลึกสดเรียลไทม์ด้วย API",
    "revenueHistory": [],
    "fcfHistory": [],
    "priceHistory": [],
    "financials": {
      "revenue": 0,
      "netIncome": 0,
      "eps": 0,
      "bookValuePerShare": 0,
      "freeCashFlow": 0,
      "ebitda": 0,
      "totalDebt": 0,
      "cash": 0,
      "dividendPerShare": 0,
      "growthRate": 0.08
    },
    "assetType": "US_STOCK",
    "currency": "USD"
  },
  {
    "symbol": "HOOD",
    "name": "Robinhood Markets, Inc. Class A Common Stock",
    "enName": "Robinhood Markets, Inc. Class A Common Stock",
    "sector": "ค้าปลีก",
    "market": "NASDAQ",
    "price": 100,
    "prevClose": 99,
    "sharesOutstanding": 1000,
    "color": "#2563EB",
    "about": "ข้อมูลหลักทรัพย์ HOOD - Robinhood Markets, Inc. Class A Common Stock จดทะเบียนในตลาด NASDAQ สหรัฐอเมริกา ดึงข้อมูลวิเคราะห์เชิงลึกสดเรียลไทม์ด้วย API",
    "revenueHistory": [],
    "fcfHistory": [],
    "priceHistory": [],
    "financials": {
      "revenue": 0,
      "netIncome": 0,
      "eps": 0,
      "bookValuePerShare": 0,
      "freeCashFlow": 0,
      "ebitda": 0,
      "totalDebt": 0,
      "cash": 0,
      "dividendPerShare": 0,
      "growthRate": 0.08
    },
    "assetType": "US_STOCK",
    "currency": "USD"
  },
  {
    "symbol": "IBIT",
    "name": "iShares Bitcoin Trust ETF",
    "enName": "iShares Bitcoin Trust ETF",
    "sector": "ธนาคาร",
    "market": "NASDAQ",
    "price": 100,
    "prevClose": 99,
    "sharesOutstanding": 1000,
    "color": "#2563EB",
    "about": "ข้อมูลหลักทรัพย์ IBIT - iShares Bitcoin Trust ETF จดทะเบียนในตลาด NASDAQ สหรัฐอเมริกา ดึงข้อมูลวิเคราะห์เชิงลึกสดเรียลไทม์ด้วย API",
    "revenueHistory": [],
    "fcfHistory": [],
    "priceHistory": [],
    "financials": {
      "revenue": 0,
      "netIncome": 0,
      "eps": 0,
      "bookValuePerShare": 0,
      "freeCashFlow": 0,
      "ebitda": 0,
      "totalDebt": 0,
      "cash": 0,
      "dividendPerShare": 0,
      "growthRate": 0.08
    },
    "assetType": "US_STOCK",
    "currency": "USD"
  },
  {
    "symbol": "IDXX",
    "name": "Idexx Laboratories Inc",
    "enName": "Idexx Laboratories Inc",
    "sector": "เทคโนโลยี",
    "market": "NASDAQ",
    "price": 100,
    "prevClose": 99,
    "sharesOutstanding": 1000,
    "color": "#2563EB",
    "about": "ข้อมูลหลักทรัพย์ IDXX - Idexx Laboratories Inc จดทะเบียนในตลาด NASDAQ สหรัฐอเมริกา ดึงข้อมูลวิเคราะห์เชิงลึกสดเรียลไทม์ด้วย API",
    "revenueHistory": [],
    "fcfHistory": [],
    "priceHistory": [],
    "financials": {
      "revenue": 0,
      "netIncome": 0,
      "eps": 0,
      "bookValuePerShare": 0,
      "freeCashFlow": 0,
      "ebitda": 0,
      "totalDebt": 0,
      "cash": 0,
      "dividendPerShare": 0,
      "growthRate": 0.08
    },
    "assetType": "US_STOCK",
    "currency": "USD"
  },
  {
    "symbol": "IEF",
    "name": "iShares 7-10 Year Treasury Bond ETF",
    "enName": "iShares 7-10 Year Treasury Bond ETF",
    "sector": "เทคโนโลยี",
    "market": "NASDAQ",
    "price": 100,
    "prevClose": 99,
    "sharesOutstanding": 1000,
    "color": "#2563EB",
    "about": "ข้อมูลหลักทรัพย์ IEF - iShares 7-10 Year Treasury Bond ETF จดทะเบียนในตลาด NASDAQ สหรัฐอเมริกา ดึงข้อมูลวิเคราะห์เชิงลึกสดเรียลไทม์ด้วย API",
    "revenueHistory": [],
    "fcfHistory": [],
    "priceHistory": [],
    "financials": {
      "revenue": 0,
      "netIncome": 0,
      "eps": 0,
      "bookValuePerShare": 0,
      "freeCashFlow": 0,
      "ebitda": 0,
      "totalDebt": 0,
      "cash": 0,
      "dividendPerShare": 0,
      "growthRate": 0.08
    },
    "assetType": "US_STOCK",
    "currency": "USD"
  },
  {
    "symbol": "ILMN",
    "name": "Illumina Inc",
    "enName": "Illumina Inc",
    "sector": "เทคโนโลยี",
    "market": "NASDAQ",
    "price": 100,
    "prevClose": 99,
    "sharesOutstanding": 1000,
    "color": "#2563EB",
    "about": "ข้อมูลหลักทรัพย์ ILMN - Illumina Inc จดทะเบียนในตลาด NASDAQ สหรัฐอเมริกา ดึงข้อมูลวิเคราะห์เชิงลึกสดเรียลไทม์ด้วย API",
    "revenueHistory": [],
    "fcfHistory": [],
    "priceHistory": [],
    "financials": {
      "revenue": 0,
      "netIncome": 0,
      "eps": 0,
      "bookValuePerShare": 0,
      "freeCashFlow": 0,
      "ebitda": 0,
      "totalDebt": 0,
      "cash": 0,
      "dividendPerShare": 0,
      "growthRate": 0.08
    },
    "assetType": "US_STOCK",
    "currency": "USD"
  },
  {
    "symbol": "INTC",
    "name": "Intel Corp",
    "enName": "Intel Corp",
    "sector": "เทคโนโลยี",
    "market": "NASDAQ",
    "price": 100,
    "prevClose": 99,
    "sharesOutstanding": 1000,
    "color": "#2563EB",
    "about": "ข้อมูลหลักทรัพย์ INTC - Intel Corp จดทะเบียนในตลาด NASDAQ สหรัฐอเมริกา ดึงข้อมูลวิเคราะห์เชิงลึกสดเรียลไทม์ด้วย API",
    "revenueHistory": [],
    "fcfHistory": [],
    "priceHistory": [],
    "financials": {
      "revenue": 0,
      "netIncome": 0,
      "eps": 0,
      "bookValuePerShare": 0,
      "freeCashFlow": 0,
      "ebitda": 0,
      "totalDebt": 0,
      "cash": 0,
      "dividendPerShare": 0,
      "growthRate": 0.08
    },
    "assetType": "US_STOCK",
    "currency": "USD"
  },
  {
    "symbol": "INTU",
    "name": "Intuit Inc",
    "enName": "Intuit Inc",
    "sector": "เทคโนโลยี",
    "market": "NASDAQ",
    "price": 100,
    "prevClose": 99,
    "sharesOutstanding": 1000,
    "color": "#2563EB",
    "about": "ข้อมูลหลักทรัพย์ INTU - Intuit Inc จดทะเบียนในตลาด NASDAQ สหรัฐอเมริกา ดึงข้อมูลวิเคราะห์เชิงลึกสดเรียลไทม์ด้วย API",
    "revenueHistory": [],
    "fcfHistory": [],
    "priceHistory": [],
    "financials": {
      "revenue": 0,
      "netIncome": 0,
      "eps": 0,
      "bookValuePerShare": 0,
      "freeCashFlow": 0,
      "ebitda": 0,
      "totalDebt": 0,
      "cash": 0,
      "dividendPerShare": 0,
      "growthRate": 0.08
    },
    "assetType": "US_STOCK",
    "currency": "USD"
  },
  {
    "symbol": "ISRG",
    "name": "Intuitive Surgical Inc.",
    "enName": "Intuitive Surgical Inc.",
    "sector": "เทคโนโลยี",
    "market": "NASDAQ",
    "price": 100,
    "prevClose": 99,
    "sharesOutstanding": 1000,
    "color": "#2563EB",
    "about": "ข้อมูลหลักทรัพย์ ISRG - Intuitive Surgical Inc. จดทะเบียนในตลาด NASDAQ สหรัฐอเมริกา ดึงข้อมูลวิเคราะห์เชิงลึกสดเรียลไทม์ด้วย API",
    "revenueHistory": [],
    "fcfHistory": [],
    "priceHistory": [],
    "financials": {
      "revenue": 0,
      "netIncome": 0,
      "eps": 0,
      "bookValuePerShare": 0,
      "freeCashFlow": 0,
      "ebitda": 0,
      "totalDebt": 0,
      "cash": 0,
      "dividendPerShare": 0,
      "growthRate": 0.08
    },
    "assetType": "US_STOCK",
    "currency": "USD"
  },
  {
    "symbol": "JD",
    "name": "JD.com, Inc.",
    "enName": "JD.com, Inc.",
    "sector": "เทคโนโลยี",
    "market": "NASDAQ",
    "price": 100,
    "prevClose": 99,
    "sharesOutstanding": 1000,
    "color": "#2563EB",
    "about": "ข้อมูลหลักทรัพย์ JD - JD.com, Inc. จดทะเบียนในตลาด NASDAQ สหรัฐอเมริกา ดึงข้อมูลวิเคราะห์เชิงลึกสดเรียลไทม์ด้วย API",
    "revenueHistory": [],
    "fcfHistory": [],
    "priceHistory": [],
    "financials": {
      "revenue": 0,
      "netIncome": 0,
      "eps": 0,
      "bookValuePerShare": 0,
      "freeCashFlow": 0,
      "ebitda": 0,
      "totalDebt": 0,
      "cash": 0,
      "dividendPerShare": 0,
      "growthRate": 0.08
    },
    "assetType": "US_STOCK",
    "currency": "USD"
  },
  {
    "symbol": "JEPQ",
    "name": "J.P. Morgan Nasdaq Equity Premium Income ETF",
    "enName": "J.P. Morgan Nasdaq Equity Premium Income ETF",
    "sector": "เทคโนโลยี",
    "market": "NASDAQ",
    "price": 100,
    "prevClose": 99,
    "sharesOutstanding": 1000,
    "color": "#2563EB",
    "about": "ข้อมูลหลักทรัพย์ JEPQ - J.P. Morgan Nasdaq Equity Premium Income ETF จดทะเบียนในตลาด NASDAQ สหรัฐอเมริกา ดึงข้อมูลวิเคราะห์เชิงลึกสดเรียลไทม์ด้วย API",
    "revenueHistory": [],
    "fcfHistory": [],
    "priceHistory": [],
    "financials": {
      "revenue": 0,
      "netIncome": 0,
      "eps": 0,
      "bookValuePerShare": 0,
      "freeCashFlow": 0,
      "ebitda": 0,
      "totalDebt": 0,
      "cash": 0,
      "dividendPerShare": 0,
      "growthRate": 0.08
    },
    "assetType": "US_STOCK",
    "currency": "USD"
  },
  {
    "symbol": "KDP",
    "name": "Keurig Dr Pepper Inc.",
    "enName": "Keurig Dr Pepper Inc.",
    "sector": "เทคโนโลยี",
    "market": "NASDAQ",
    "price": 100,
    "prevClose": 99,
    "sharesOutstanding": 1000,
    "color": "#2563EB",
    "about": "ข้อมูลหลักทรัพย์ KDP - Keurig Dr Pepper Inc. จดทะเบียนในตลาด NASDAQ สหรัฐอเมริกา ดึงข้อมูลวิเคราะห์เชิงลึกสดเรียลไทม์ด้วย API",
    "revenueHistory": [],
    "fcfHistory": [],
    "priceHistory": [],
    "financials": {
      "revenue": 0,
      "netIncome": 0,
      "eps": 0,
      "bookValuePerShare": 0,
      "freeCashFlow": 0,
      "ebitda": 0,
      "totalDebt": 0,
      "cash": 0,
      "dividendPerShare": 0,
      "growthRate": 0.08
    },
    "assetType": "US_STOCK",
    "currency": "USD"
  },
  {
    "symbol": "LCID",
    "name": "Lucid Group, Inc. Common Stock",
    "enName": "Lucid Group, Inc. Common Stock",
    "sector": "เทคโนโลยี",
    "market": "NASDAQ",
    "price": 100,
    "prevClose": 99,
    "sharesOutstanding": 1000,
    "color": "#2563EB",
    "about": "ข้อมูลหลักทรัพย์ LCID - Lucid Group, Inc. Common Stock จดทะเบียนในตลาด NASDAQ สหรัฐอเมริกา ดึงข้อมูลวิเคราะห์เชิงลึกสดเรียลไทม์ด้วย API",
    "revenueHistory": [],
    "fcfHistory": [],
    "priceHistory": [],
    "financials": {
      "revenue": 0,
      "netIncome": 0,
      "eps": 0,
      "bookValuePerShare": 0,
      "freeCashFlow": 0,
      "ebitda": 0,
      "totalDebt": 0,
      "cash": 0,
      "dividendPerShare": 0,
      "growthRate": 0.08
    },
    "assetType": "US_STOCK",
    "currency": "USD"
  },
  {
    "symbol": "LRCX",
    "name": "Lam Research Corp",
    "enName": "Lam Research Corp",
    "sector": "เทคโนโลยี",
    "market": "NASDAQ",
    "price": 100,
    "prevClose": 99,
    "sharesOutstanding": 1000,
    "color": "#2563EB",
    "about": "ข้อมูลหลักทรัพย์ LRCX - Lam Research Corp จดทะเบียนในตลาด NASDAQ สหรัฐอเมริกา ดึงข้อมูลวิเคราะห์เชิงลึกสดเรียลไทม์ด้วย API",
    "revenueHistory": [],
    "fcfHistory": [],
    "priceHistory": [],
    "financials": {
      "revenue": 0,
      "netIncome": 0,
      "eps": 0,
      "bookValuePerShare": 0,
      "freeCashFlow": 0,
      "ebitda": 0,
      "totalDebt": 0,
      "cash": 0,
      "dividendPerShare": 0,
      "growthRate": 0.08
    },
    "assetType": "US_STOCK",
    "currency": "USD"
  },
  {
    "symbol": "LULU",
    "name": "lululemon athletica inc.",
    "enName": "lululemon athletica inc.",
    "sector": "เทคโนโลยี",
    "market": "NASDAQ",
    "price": 100,
    "prevClose": 99,
    "sharesOutstanding": 1000,
    "color": "#2563EB",
    "about": "ข้อมูลหลักทรัพย์ LULU - lululemon athletica inc. จดทะเบียนในตลาด NASDAQ สหรัฐอเมริกา ดึงข้อมูลวิเคราะห์เชิงลึกสดเรียลไทม์ด้วย API",
    "revenueHistory": [],
    "fcfHistory": [],
    "priceHistory": [],
    "financials": {
      "revenue": 0,
      "netIncome": 0,
      "eps": 0,
      "bookValuePerShare": 0,
      "freeCashFlow": 0,
      "ebitda": 0,
      "totalDebt": 0,
      "cash": 0,
      "dividendPerShare": 0,
      "growthRate": 0.08
    },
    "assetType": "US_STOCK",
    "currency": "USD"
  },
  {
    "symbol": "MAR",
    "name": "Marriott International Class A Common Stock",
    "enName": "Marriott International Class A Common Stock",
    "sector": "เทคโนโลยี",
    "market": "NASDAQ",
    "price": 100,
    "prevClose": 99,
    "sharesOutstanding": 1000,
    "color": "#2563EB",
    "about": "ข้อมูลหลักทรัพย์ MAR - Marriott International Class A Common Stock จดทะเบียนในตลาด NASDAQ สหรัฐอเมริกา ดึงข้อมูลวิเคราะห์เชิงลึกสดเรียลไทม์ด้วย API",
    "revenueHistory": [],
    "fcfHistory": [],
    "priceHistory": [],
    "financials": {
      "revenue": 0,
      "netIncome": 0,
      "eps": 0,
      "bookValuePerShare": 0,
      "freeCashFlow": 0,
      "ebitda": 0,
      "totalDebt": 0,
      "cash": 0,
      "dividendPerShare": 0,
      "growthRate": 0.08
    },
    "assetType": "US_STOCK",
    "currency": "USD"
  },
  {
    "symbol": "MCHP",
    "name": "Microchip Technology Inc",
    "enName": "Microchip Technology Inc",
    "sector": "เทคโนโลยี",
    "market": "NASDAQ",
    "price": 100,
    "prevClose": 99,
    "sharesOutstanding": 1000,
    "color": "#2563EB",
    "about": "ข้อมูลหลักทรัพย์ MCHP - Microchip Technology Inc จดทะเบียนในตลาด NASDAQ สหรัฐอเมริกา ดึงข้อมูลวิเคราะห์เชิงลึกสดเรียลไทม์ด้วย API",
    "revenueHistory": [],
    "fcfHistory": [],
    "priceHistory": [],
    "financials": {
      "revenue": 0,
      "netIncome": 0,
      "eps": 0,
      "bookValuePerShare": 0,
      "freeCashFlow": 0,
      "ebitda": 0,
      "totalDebt": 0,
      "cash": 0,
      "dividendPerShare": 0,
      "growthRate": 0.08
    },
    "assetType": "US_STOCK",
    "currency": "USD"
  },
  {
    "symbol": "MDB",
    "name": "MongoDB, Inc. Class A",
    "enName": "MongoDB, Inc. Class A",
    "sector": "เทคโนโลยี",
    "market": "NASDAQ",
    "price": 100,
    "prevClose": 99,
    "sharesOutstanding": 1000,
    "color": "#2563EB",
    "about": "ข้อมูลหลักทรัพย์ MDB - MongoDB, Inc. Class A จดทะเบียนในตลาด NASDAQ สหรัฐอเมริกา พร้อมข้อมูลวิเคราะห์เชิงลึกสำหรับประกอบการตัดสินใจ",
    "revenueHistory": [],
    "fcfHistory": [],
    "priceHistory": [],
    "financials": {
      "revenue": 0,
      "netIncome": 0,
      "eps": 0,
      "bookValuePerShare": 0,
      "freeCashFlow": 0,
      "ebitda": 0,
      "totalDebt": 0,
      "cash": 0,
      "dividendPerShare": 0,
      "growthRate": 0.08
    },
    "assetType": "US_STOCK",
    "currency": "USD"
  },
  {
    "symbol": "MDLZ",
    "name": "Mondelez International, Inc. Class A",
    "enName": "Mondelez International, Inc. Class A",
    "sector": "เทคโนโลยี",
    "market": "NASDAQ",
    "price": 100,
    "prevClose": 99,
    "sharesOutstanding": 1000,
    "color": "#2563EB",
    "about": "ข้อมูลหลักทรัพย์ MDLZ - Mondelez International, Inc. Class A จดทะเบียนในตลาด NASDAQ สหรัฐอเมริกา ดึงข้อมูลวิเคราะห์เชิงลึกสดเรียลไทม์ด้วย API",
    "revenueHistory": [],
    "fcfHistory": [],
    "priceHistory": [],
    "financials": {
      "revenue": 0,
      "netIncome": 0,
      "eps": 0,
      "bookValuePerShare": 0,
      "freeCashFlow": 0,
      "ebitda": 0,
      "totalDebt": 0,
      "cash": 0,
      "dividendPerShare": 0,
      "growthRate": 0.08
    },
    "assetType": "US_STOCK",
    "currency": "USD"
  },
  {
    "symbol": "META",
    "name": "Meta Platforms, Inc. Class A Common Stock",
    "enName": "Meta Platforms, Inc. Class A Common Stock",
    "sector": "เทคโนโลยี",
    "market": "NASDAQ",
    "price": 100,
    "prevClose": 99,
    "sharesOutstanding": 1000,
    "color": "#2563EB",
    "about": "ข้อมูลหลักทรัพย์ META - Meta Platforms, Inc. Class A Common Stock จดทะเบียนในตลาด NASDAQ สหรัฐอเมริกา ดึงข้อมูลวิเคราะห์เชิงลึกสดเรียลไทม์ด้วย API",
    "revenueHistory": [],
    "fcfHistory": [],
    "priceHistory": [],
    "financials": {
      "revenue": 0,
      "netIncome": 0,
      "eps": 0,
      "bookValuePerShare": 0,
      "freeCashFlow": 0,
      "ebitda": 0,
      "totalDebt": 0,
      "cash": 0,
      "dividendPerShare": 0,
      "growthRate": 0.08
    },
    "assetType": "US_STOCK",
    "currency": "USD"
  },
  {
    "symbol": "MNST",
    "name": "Monster Beverage Corporation",
    "enName": "Monster Beverage Corporation",
    "sector": "ค้าปลีก",
    "market": "NASDAQ",
    "price": 100,
    "prevClose": 99,
    "sharesOutstanding": 1000,
    "color": "#2563EB",
    "about": "ข้อมูลหลักทรัพย์ MNST - Monster Beverage Corporation จดทะเบียนในตลาด NASDAQ สหรัฐอเมริกา ดึงข้อมูลวิเคราะห์เชิงลึกสดเรียลไทม์ด้วย API",
    "revenueHistory": [],
    "fcfHistory": [],
    "priceHistory": [],
    "financials": {
      "revenue": 0,
      "netIncome": 0,
      "eps": 0,
      "bookValuePerShare": 0,
      "freeCashFlow": 0,
      "ebitda": 0,
      "totalDebt": 0,
      "cash": 0,
      "dividendPerShare": 0,
      "growthRate": 0.08
    },
    "assetType": "US_STOCK",
    "currency": "USD"
  },
  {
    "symbol": "MRNA",
    "name": "Moderna, Inc. Common Stock",
    "enName": "Moderna, Inc. Common Stock",
    "sector": "เทคโนโลยี",
    "market": "NASDAQ",
    "price": 100,
    "prevClose": 99,
    "sharesOutstanding": 1000,
    "color": "#2563EB",
    "about": "ข้อมูลหลักทรัพย์ MRNA - Moderna, Inc. Common Stock จดทะเบียนในตลาด NASDAQ สหรัฐอเมริกา ดึงข้อมูลวิเคราะห์เชิงลึกสดเรียลไทม์ด้วย API",
    "revenueHistory": [],
    "fcfHistory": [],
    "priceHistory": [],
    "financials": {
      "revenue": 0,
      "netIncome": 0,
      "eps": 0,
      "bookValuePerShare": 0,
      "freeCashFlow": 0,
      "ebitda": 0,
      "totalDebt": 0,
      "cash": 0,
      "dividendPerShare": 0,
      "growthRate": 0.08
    },
    "assetType": "US_STOCK",
    "currency": "USD"
  },
  {
    "symbol": "MRVL",
    "name": "Marvell Technology, Inc. Common Stock",
    "enName": "Marvell Technology, Inc. Common Stock",
    "sector": "เทคโนโลยี",
    "market": "NASDAQ",
    "price": 100,
    "prevClose": 99,
    "sharesOutstanding": 1000,
    "color": "#2563EB",
    "about": "ข้อมูลหลักทรัพย์ MRVL - Marvell Technology, Inc. Common Stock จดทะเบียนในตลาด NASDAQ สหรัฐอเมริกา ดึงข้อมูลวิเคราะห์เชิงลึกสดเรียลไทม์ด้วย API",
    "revenueHistory": [],
    "fcfHistory": [],
    "priceHistory": [],
    "financials": {
      "revenue": 0,
      "netIncome": 0,
      "eps": 0,
      "bookValuePerShare": 0,
      "freeCashFlow": 0,
      "ebitda": 0,
      "totalDebt": 0,
      "cash": 0,
      "dividendPerShare": 0,
      "growthRate": 0.08
    },
    "assetType": "US_STOCK",
    "currency": "USD"
  },
  {
    "symbol": "MSFT",
    "name": "Microsoft Corp",
    "enName": "Microsoft Corp",
    "sector": "เทคโนโลยี",
    "market": "NASDAQ",
    "price": 100,
    "prevClose": 99,
    "sharesOutstanding": 1000,
    "color": "#2563EB",
    "about": "ข้อมูลหลักทรัพย์ MSFT - Microsoft Corp จดทะเบียนในตลาด NASDAQ สหรัฐอเมริกา ดึงข้อมูลวิเคราะห์เชิงลึกสดเรียลไทม์ด้วย API",
    "revenueHistory": [],
    "fcfHistory": [],
    "priceHistory": [],
    "financials": {
      "revenue": 0,
      "netIncome": 0,
      "eps": 0,
      "bookValuePerShare": 0,
      "freeCashFlow": 0,
      "ebitda": 0,
      "totalDebt": 0,
      "cash": 0,
      "dividendPerShare": 0,
      "growthRate": 0.08
    },
    "assetType": "US_STOCK",
    "currency": "USD"
  },
  {
    "symbol": "MSTR",
    "name": "Strategy Inc Common Stock Class A",
    "enName": "Strategy Inc Common Stock Class A",
    "sector": "เทคโนโลยี",
    "market": "NASDAQ",
    "price": 100,
    "prevClose": 99,
    "sharesOutstanding": 1000,
    "color": "#2563EB",
    "about": "ข้อมูลหลักทรัพย์ MSTR - Strategy Inc Common Stock Class A จดทะเบียนในตลาด NASDAQ สหรัฐอเมริกา ดึงข้อมูลวิเคราะห์เชิงลึกสดเรียลไทม์ด้วย API",
    "revenueHistory": [],
    "fcfHistory": [],
    "priceHistory": [],
    "financials": {
      "revenue": 0,
      "netIncome": 0,
      "eps": 0,
      "bookValuePerShare": 0,
      "freeCashFlow": 0,
      "ebitda": 0,
      "totalDebt": 0,
      "cash": 0,
      "dividendPerShare": 0,
      "growthRate": 0.08
    },
    "assetType": "US_STOCK",
    "currency": "USD"
  },
  {
    "symbol": "MU",
    "name": "Micron Technology, Inc.",
    "enName": "Micron Technology, Inc.",
    "sector": "เทคโนโลยี",
    "market": "NASDAQ",
    "price": 100,
    "prevClose": 99,
    "sharesOutstanding": 1000,
    "color": "#2563EB",
    "about": "ข้อมูลหลักทรัพย์ MU - Micron Technology, Inc. จดทะเบียนในตลาด NASDAQ สหรัฐอเมริกา ดึงข้อมูลวิเคราะห์เชิงลึกสดเรียลไทม์ด้วย API",
    "revenueHistory": [],
    "fcfHistory": [],
    "priceHistory": [],
    "financials": {
      "revenue": 0,
      "netIncome": 0,
      "eps": 0,
      "bookValuePerShare": 0,
      "freeCashFlow": 0,
      "ebitda": 0,
      "totalDebt": 0,
      "cash": 0,
      "dividendPerShare": 0,
      "growthRate": 0.08
    },
    "assetType": "US_STOCK",
    "currency": "USD"
  },
  {
    "symbol": "NFLX",
    "name": "NetFlix Inc",
    "enName": "NetFlix Inc",
    "sector": "เทคโนโลยี",
    "market": "NASDAQ",
    "price": 100,
    "prevClose": 99,
    "sharesOutstanding": 1000,
    "color": "#2563EB",
    "about": "ข้อมูลหลักทรัพย์ NFLX - NetFlix Inc จดทะเบียนในตลาด NASDAQ สหรัฐอเมริกา ดึงข้อมูลวิเคราะห์เชิงลึกสดเรียลไทม์ด้วย API",
    "revenueHistory": [],
    "fcfHistory": [],
    "priceHistory": [],
    "financials": {
      "revenue": 0,
      "netIncome": 0,
      "eps": 0,
      "bookValuePerShare": 0,
      "freeCashFlow": 0,
      "ebitda": 0,
      "totalDebt": 0,
      "cash": 0,
      "dividendPerShare": 0,
      "growthRate": 0.08
    },
    "assetType": "US_STOCK",
    "currency": "USD"
  },
  {
    "symbol": "NTES",
    "name": "NetEase, inc.",
    "enName": "NetEase, inc.",
    "sector": "เทคโนโลยี",
    "market": "NASDAQ",
    "price": 100,
    "prevClose": 99,
    "sharesOutstanding": 1000,
    "color": "#2563EB",
    "about": "ข้อมูลหลักทรัพย์ NTES - NetEase, inc. จดทะเบียนในตลาด NASDAQ สหรัฐอเมริกา ดึงข้อมูลวิเคราะห์เชิงลึกสดเรียลไทม์ด้วย API",
    "revenueHistory": [],
    "fcfHistory": [],
    "priceHistory": [],
    "financials": {
      "revenue": 0,
      "netIncome": 0,
      "eps": 0,
      "bookValuePerShare": 0,
      "freeCashFlow": 0,
      "ebitda": 0,
      "totalDebt": 0,
      "cash": 0,
      "dividendPerShare": 0,
      "growthRate": 0.08
    },
    "assetType": "US_STOCK",
    "currency": "USD"
  },
  {
    "symbol": "NVDA",
    "name": "Nvidia Corp",
    "enName": "Nvidia Corp",
    "sector": "เทคโนโลยี",
    "market": "NASDAQ",
    "price": 100,
    "prevClose": 99,
    "sharesOutstanding": 1000,
    "color": "#2563EB",
    "about": "ข้อมูลหลักทรัพย์ NVDA - Nvidia Corp จดทะเบียนในตลาด NASDAQ สหรัฐอเมริกา ดึงข้อมูลวิเคราะห์เชิงลึกสดเรียลไทม์ด้วย API",
    "revenueHistory": [],
    "fcfHistory": [],
    "priceHistory": [],
    "financials": {
      "revenue": 0,
      "netIncome": 0,
      "eps": 0,
      "bookValuePerShare": 0,
      "freeCashFlow": 0,
      "ebitda": 0,
      "totalDebt": 0,
      "cash": 0,
      "dividendPerShare": 0,
      "growthRate": 0.08
    },
    "assetType": "US_STOCK",
    "currency": "USD"
  },
  {
    "symbol": "NXPI",
    "name": "NXP Semiconductors N.V.",
    "enName": "NXP Semiconductors N.V.",
    "sector": "เทคโนโลยี",
    "market": "NASDAQ",
    "price": 100,
    "prevClose": 99,
    "sharesOutstanding": 1000,
    "color": "#2563EB",
    "about": "ข้อมูลหลักทรัพย์ NXPI - NXP Semiconductors N.V. จดทะเบียนในตลาด NASDAQ สหรัฐอเมริกา ดึงข้อมูลวิเคราะห์เชิงลึกสดเรียลไทม์ด้วย API",
    "revenueHistory": [],
    "fcfHistory": [],
    "priceHistory": [],
    "financials": {
      "revenue": 0,
      "netIncome": 0,
      "eps": 0,
      "bookValuePerShare": 0,
      "freeCashFlow": 0,
      "ebitda": 0,
      "totalDebt": 0,
      "cash": 0,
      "dividendPerShare": 0,
      "growthRate": 0.08
    },
    "assetType": "US_STOCK",
    "currency": "USD"
  },
  {
    "symbol": "ODFL",
    "name": "Old Dominion Freight Line",
    "enName": "Old Dominion Freight Line",
    "sector": "เทคโนโลยี",
    "market": "NASDAQ",
    "price": 100,
    "prevClose": 99,
    "sharesOutstanding": 1000,
    "color": "#2563EB",
    "about": "ข้อมูลหลักทรัพย์ ODFL - Old Dominion Freight Line จดทะเบียนในตลาด NASDAQ สหรัฐอเมริกา ดึงข้อมูลวิเคราะห์เชิงลึกสดเรียลไทม์ด้วย API",
    "revenueHistory": [],
    "fcfHistory": [],
    "priceHistory": [],
    "financials": {
      "revenue": 0,
      "netIncome": 0,
      "eps": 0,
      "bookValuePerShare": 0,
      "freeCashFlow": 0,
      "ebitda": 0,
      "totalDebt": 0,
      "cash": 0,
      "dividendPerShare": 0,
      "growthRate": 0.08
    },
    "assetType": "US_STOCK",
    "currency": "USD"
  },
  {
    "symbol": "OKTA",
    "name": "Okta, Inc. Class A Common Stock",
    "enName": "Okta, Inc. Class A Common Stock",
    "sector": "เทคโนโลยี",
    "market": "NASDAQ",
    "price": 100,
    "prevClose": 99,
    "sharesOutstanding": 1000,
    "color": "#2563EB",
    "about": "ข้อมูลหลักทรัพย์ OKTA - Okta, Inc. Class A Common Stock จดทะเบียนในตลาด NASDAQ สหรัฐอเมริกา ดึงข้อมูลวิเคราะห์เชิงลึกสดเรียลไทม์ด้วย API",
    "revenueHistory": [],
    "fcfHistory": [],
    "priceHistory": [],
    "financials": {
      "revenue": 0,
      "netIncome": 0,
      "eps": 0,
      "bookValuePerShare": 0,
      "freeCashFlow": 0,
      "ebitda": 0,
      "totalDebt": 0,
      "cash": 0,
      "dividendPerShare": 0,
      "growthRate": 0.08
    },
    "assetType": "US_STOCK",
    "currency": "USD"
  },
  {
    "symbol": "ON",
    "name": "ON Semiconductor Corp",
    "enName": "ON Semiconductor Corp",
    "sector": "เทคโนโลยี",
    "market": "NASDAQ",
    "price": 100,
    "prevClose": 99,
    "sharesOutstanding": 1000,
    "color": "#2563EB",
    "about": "ข้อมูลหลักทรัพย์ ON - ON Semiconductor Corp จดทะเบียนในตลาด NASDAQ สหรัฐอเมริกา ดึงข้อมูลวิเคราะห์เชิงลึกสดเรียลไทม์ด้วย API",
    "revenueHistory": [],
    "fcfHistory": [],
    "priceHistory": [],
    "financials": {
      "revenue": 0,
      "netIncome": 0,
      "eps": 0,
      "bookValuePerShare": 0,
      "freeCashFlow": 0,
      "ebitda": 0,
      "totalDebt": 0,
      "cash": 0,
      "dividendPerShare": 0,
      "growthRate": 0.08
    },
    "assetType": "US_STOCK",
    "currency": "USD"
  },
  {
    "symbol": "ORLY",
    "name": "O'Reilly Automotive, Inc.",
    "enName": "O'Reilly Automotive, Inc.",
    "sector": "เทคโนโลยี",
    "market": "NASDAQ",
    "price": 100,
    "prevClose": 99,
    "sharesOutstanding": 1000,
    "color": "#2563EB",
    "about": "ข้อมูลหลักทรัพย์ ORLY - O'Reilly Automotive, Inc. จดทะเบียนในตลาด NASDAQ สหรัฐอเมริกา ดึงข้อมูลวิเคราะห์เชิงลึกสดเรียลไทม์ด้วย API",
    "revenueHistory": [],
    "fcfHistory": [],
    "priceHistory": [],
    "financials": {
      "revenue": 0,
      "netIncome": 0,
      "eps": 0,
      "bookValuePerShare": 0,
      "freeCashFlow": 0,
      "ebitda": 0,
      "totalDebt": 0,
      "cash": 0,
      "dividendPerShare": 0,
      "growthRate": 0.08
    },
    "assetType": "US_STOCK",
    "currency": "USD"
  },
  {
    "symbol": "PANW",
    "name": "Palo Alto Networks, Inc. Common Stock",
    "enName": "Palo Alto Networks, Inc. Common Stock",
    "sector": "เทคโนโลยี",
    "market": "NASDAQ",
    "price": 100,
    "prevClose": 99,
    "sharesOutstanding": 1000,
    "color": "#2563EB",
    "about": "ข้อมูลหลักทรัพย์ PANW - Palo Alto Networks, Inc. Common Stock จดทะเบียนในตลาด NASDAQ สหรัฐอเมริกา ดึงข้อมูลวิเคราะห์เชิงลึกสดเรียลไทม์ด้วย API",
    "revenueHistory": [],
    "fcfHistory": [],
    "priceHistory": [],
    "financials": {
      "revenue": 0,
      "netIncome": 0,
      "eps": 0,
      "bookValuePerShare": 0,
      "freeCashFlow": 0,
      "ebitda": 0,
      "totalDebt": 0,
      "cash": 0,
      "dividendPerShare": 0,
      "growthRate": 0.08
    },
    "assetType": "US_STOCK",
    "currency": "USD"
  },
  {
    "symbol": "PAYX",
    "name": "Paychex Inc",
    "enName": "Paychex Inc",
    "sector": "เทคโนโลยี",
    "market": "NASDAQ",
    "price": 100,
    "prevClose": 99,
    "sharesOutstanding": 1000,
    "color": "#2563EB",
    "about": "ข้อมูลหลักทรัพย์ PAYX - Paychex Inc จดทะเบียนในตลาด NASDAQ สหรัฐอเมริกา ดึงข้อมูลวิเคราะห์เชิงลึกสดเรียลไทม์ด้วย API",
    "revenueHistory": [],
    "fcfHistory": [],
    "priceHistory": [],
    "financials": {
      "revenue": 0,
      "netIncome": 0,
      "eps": 0,
      "bookValuePerShare": 0,
      "freeCashFlow": 0,
      "ebitda": 0,
      "totalDebt": 0,
      "cash": 0,
      "dividendPerShare": 0,
      "growthRate": 0.08
    },
    "assetType": "US_STOCK",
    "currency": "USD"
  },
  {
    "symbol": "PCAR",
    "name": "Paccar Inc",
    "enName": "Paccar Inc",
    "sector": "เทคโนโลยี",
    "market": "NASDAQ",
    "price": 100,
    "prevClose": 99,
    "sharesOutstanding": 1000,
    "color": "#2563EB",
    "about": "ข้อมูลหลักทรัพย์ PCAR - Paccar Inc จดทะเบียนในตลาด NASDAQ สหรัฐอเมริกา ดึงข้อมูลวิเคราะห์เชิงลึกสดเรียลไทม์ด้วย API",
    "revenueHistory": [],
    "fcfHistory": [],
    "priceHistory": [],
    "financials": {
      "revenue": 0,
      "netIncome": 0,
      "eps": 0,
      "bookValuePerShare": 0,
      "freeCashFlow": 0,
      "ebitda": 0,
      "totalDebt": 0,
      "cash": 0,
      "dividendPerShare": 0,
      "growthRate": 0.08
    },
    "assetType": "US_STOCK",
    "currency": "USD"
  },
  {
    "symbol": "PDD",
    "name": "PDD Holdings Inc. American Depositary Shares",
    "enName": "PDD Holdings Inc. American Depositary Shares",
    "sector": "ธนาคาร",
    "market": "NASDAQ",
    "price": 100,
    "prevClose": 99,
    "sharesOutstanding": 1000,
    "color": "#2563EB",
    "about": "ข้อมูลหลักทรัพย์ PDD - PDD Holdings Inc. American Depositary Shares จดทะเบียนในตลาด NASDAQ สหรัฐอเมริกา ดึงข้อมูลวิเคราะห์เชิงลึกสดเรียลไทม์ด้วย API",
    "revenueHistory": [],
    "fcfHistory": [],
    "priceHistory": [],
    "financials": {
      "revenue": 0,
      "netIncome": 0,
      "eps": 0,
      "bookValuePerShare": 0,
      "freeCashFlow": 0,
      "ebitda": 0,
      "totalDebt": 0,
      "cash": 0,
      "dividendPerShare": 0,
      "growthRate": 0.08
    },
    "assetType": "US_STOCK",
    "currency": "USD"
  },
  {
    "symbol": "PEP",
    "name": "PepsiCo, Inc.",
    "enName": "PepsiCo, Inc.",
    "sector": "เทคโนโลยี",
    "market": "NASDAQ",
    "price": 100,
    "prevClose": 99,
    "sharesOutstanding": 1000,
    "color": "#2563EB",
    "about": "ข้อมูลหลักทรัพย์ PEP - PepsiCo, Inc. จดทะเบียนในตลาด NASDAQ สหรัฐอเมริกา ดึงข้อมูลวิเคราะห์เชิงลึกสดเรียลไทม์ด้วย API",
    "revenueHistory": [],
    "fcfHistory": [],
    "priceHistory": [],
    "financials": {
      "revenue": 0,
      "netIncome": 0,
      "eps": 0,
      "bookValuePerShare": 0,
      "freeCashFlow": 0,
      "ebitda": 0,
      "totalDebt": 0,
      "cash": 0,
      "dividendPerShare": 0,
      "growthRate": 0.08
    },
    "assetType": "US_STOCK",
    "currency": "USD"
  },
  {
    "symbol": "PLTR",
    "name": "Palantir Technologies Inc. Class A Common Stock",
    "enName": "Palantir Technologies Inc. Class A Common Stock",
    "sector": "เทคโนโลยี",
    "market": "NASDAQ",
    "price": 100,
    "prevClose": 99,
    "sharesOutstanding": 1000,
    "color": "#2563EB",
    "about": "ข้อมูลหลักทรัพย์ PLTR - Palantir Technologies Inc. Class A Common Stock จดทะเบียนในตลาด NASDAQ สหรัฐอเมริกา ดึงข้อมูลวิเคราะห์เชิงลึกสดเรียลไทม์ด้วย API",
    "revenueHistory": [],
    "fcfHistory": [],
    "priceHistory": [],
    "financials": {
      "revenue": 0,
      "netIncome": 0,
      "eps": 0,
      "bookValuePerShare": 0,
      "freeCashFlow": 0,
      "ebitda": 0,
      "totalDebt": 0,
      "cash": 0,
      "dividendPerShare": 0,
      "growthRate": 0.08
    },
    "assetType": "US_STOCK",
    "currency": "USD"
  },
  {
    "symbol": "PTON",
    "name": "Peloton Interactive, Inc. Class A Common Stock",
    "enName": "Peloton Interactive, Inc. Class A Common Stock",
    "sector": "เทคโนโลยี",
    "market": "NASDAQ",
    "price": 100,
    "prevClose": 99,
    "sharesOutstanding": 1000,
    "color": "#2563EB",
    "about": "ข้อมูลหลักทรัพย์ PTON - Peloton Interactive, Inc. Class A Common Stock จดทะเบียนในตลาด NASDAQ สหรัฐอเมริกา ดึงข้อมูลวิเคราะห์เชิงลึกสดเรียลไทม์ด้วย API",
    "revenueHistory": [],
    "fcfHistory": [],
    "priceHistory": [],
    "financials": {
      "revenue": 0,
      "netIncome": 0,
      "eps": 0,
      "bookValuePerShare": 0,
      "freeCashFlow": 0,
      "ebitda": 0,
      "totalDebt": 0,
      "cash": 0,
      "dividendPerShare": 0,
      "growthRate": 0.08
    },
    "assetType": "US_STOCK",
    "currency": "USD"
  },
  {
    "symbol": "PYPL",
    "name": "PayPal Holdings, Inc. Common Stock",
    "enName": "PayPal Holdings, Inc. Common Stock",
    "sector": "ธนาคาร",
    "market": "NASDAQ",
    "price": 100,
    "prevClose": 99,
    "sharesOutstanding": 1000,
    "color": "#2563EB",
    "about": "ข้อมูลหลักทรัพย์ PYPL - PayPal Holdings, Inc. Common Stock จดทะเบียนในตลาด NASDAQ สหรัฐอเมริกา ดึงข้อมูลวิเคราะห์เชิงลึกสดเรียลไทม์ด้วย API",
    "revenueHistory": [],
    "fcfHistory": [],
    "priceHistory": [],
    "financials": {
      "revenue": 0,
      "netIncome": 0,
      "eps": 0,
      "bookValuePerShare": 0,
      "freeCashFlow": 0,
      "ebitda": 0,
      "totalDebt": 0,
      "cash": 0,
      "dividendPerShare": 0,
      "growthRate": 0.08
    },
    "assetType": "US_STOCK",
    "currency": "USD"
  },
  {
    "symbol": "QCOM",
    "name": "Qualcomm Inc",
    "enName": "Qualcomm Inc",
    "sector": "เทคโนโลยี",
    "market": "NASDAQ",
    "price": 100,
    "prevClose": 99,
    "sharesOutstanding": 1000,
    "color": "#2563EB",
    "about": "ข้อมูลหลักทรัพย์ QCOM - Qualcomm Inc จดทะเบียนในตลาด NASDAQ สหรัฐอเมริกา ดึงข้อมูลวิเคราะห์เชิงลึกสดเรียลไทม์ด้วย API",
    "revenueHistory": [],
    "fcfHistory": [],
    "priceHistory": [],
    "financials": {
      "revenue": 0,
      "netIncome": 0,
      "eps": 0,
      "bookValuePerShare": 0,
      "freeCashFlow": 0,
      "ebitda": 0,
      "totalDebt": 0,
      "cash": 0,
      "dividendPerShare": 0,
      "growthRate": 0.08
    },
    "assetType": "US_STOCK",
    "currency": "USD"
  },
  {
    "symbol": "QQQ",
    "name": "Invesco QQQ Trust, Series 1",
    "enName": "Invesco QQQ Trust, Series 1",
    "sector": "ธนาคาร",
    "market": "NASDAQ",
    "price": 100,
    "prevClose": 99,
    "sharesOutstanding": 1000,
    "color": "#2563EB",
    "about": "ข้อมูลหลักทรัพย์ QQQ - Invesco QQQ Trust, Series 1 จดทะเบียนในตลาด NASDAQ สหรัฐอเมริกา ดึงข้อมูลวิเคราะห์เชิงลึกสดเรียลไทม์ด้วย API",
    "revenueHistory": [],
    "fcfHistory": [],
    "priceHistory": [],
    "financials": {
      "revenue": 0,
      "netIncome": 0,
      "eps": 0,
      "bookValuePerShare": 0,
      "freeCashFlow": 0,
      "ebitda": 0,
      "totalDebt": 0,
      "cash": 0,
      "dividendPerShare": 0,
      "growthRate": 0.08
    },
    "assetType": "US_STOCK",
    "currency": "USD"
  },
  {
    "symbol": "QYLD",
    "name": "Global X Funds Global X NASDAQ-100 Covered Call ETF",
    "enName": "Global X Funds Global X NASDAQ-100 Covered Call ETF",
    "sector": "เทคโนโลยี",
    "market": "NASDAQ",
    "price": 100,
    "prevClose": 99,
    "sharesOutstanding": 1000,
    "color": "#2563EB",
    "about": "ข้อมูลหลักทรัพย์ QYLD - Global X Funds Global X NASDAQ-100 Covered Call ETF จดทะเบียนในตลาด NASDAQ สหรัฐอเมริกา ดึงข้อมูลวิเคราะห์เชิงลึกสดเรียลไทม์ด้วย API",
    "revenueHistory": [],
    "fcfHistory": [],
    "priceHistory": [],
    "financials": {
      "revenue": 0,
      "netIncome": 0,
      "eps": 0,
      "bookValuePerShare": 0,
      "freeCashFlow": 0,
      "ebitda": 0,
      "totalDebt": 0,
      "cash": 0,
      "dividendPerShare": 0,
      "growthRate": 0.08
    },
    "assetType": "US_STOCK",
    "currency": "USD"
  },
  {
    "symbol": "REGN",
    "name": "Regeneron Pharmaceuticals Inc",
    "enName": "Regeneron Pharmaceuticals Inc",
    "sector": "การแพทย์",
    "market": "NASDAQ",
    "price": 100,
    "prevClose": 99,
    "sharesOutstanding": 1000,
    "color": "#2563EB",
    "about": "ข้อมูลหลักทรัพย์ REGN - Regeneron Pharmaceuticals Inc จดทะเบียนในตลาด NASDAQ สหรัฐอเมริกา ดึงข้อมูลวิเคราะห์เชิงลึกสดเรียลไทม์ด้วย API",
    "revenueHistory": [],
    "fcfHistory": [],
    "priceHistory": [],
    "financials": {
      "revenue": 0,
      "netIncome": 0,
      "eps": 0,
      "bookValuePerShare": 0,
      "freeCashFlow": 0,
      "ebitda": 0,
      "totalDebt": 0,
      "cash": 0,
      "dividendPerShare": 0,
      "growthRate": 0.08
    },
    "assetType": "US_STOCK",
    "currency": "USD"
  },
  {
    "symbol": "RIVN",
    "name": "Rivian Automotive, Inc. Class A Common Stock",
    "enName": "Rivian Automotive, Inc. Class A Common Stock",
    "sector": "เทคโนโลยี",
    "market": "NASDAQ",
    "price": 100,
    "prevClose": 99,
    "sharesOutstanding": 1000,
    "color": "#2563EB",
    "about": "ข้อมูลหลักทรัพย์ RIVN - Rivian Automotive, Inc. Class A Common Stock จดทะเบียนในตลาด NASDAQ สหรัฐอเมริกา ดึงข้อมูลวิเคราะห์เชิงลึกสดเรียลไทม์ด้วย API",
    "revenueHistory": [],
    "fcfHistory": [],
    "priceHistory": [],
    "financials": {
      "revenue": 0,
      "netIncome": 0,
      "eps": 0,
      "bookValuePerShare": 0,
      "freeCashFlow": 0,
      "ebitda": 0,
      "totalDebt": 0,
      "cash": 0,
      "dividendPerShare": 0,
      "growthRate": 0.08
    },
    "assetType": "US_STOCK",
    "currency": "USD"
  },
  {
    "symbol": "ROKU",
    "name": "Roku, Inc. Class A Common Stock",
    "enName": "Roku, Inc. Class A Common Stock",
    "sector": "เทคโนโลยี",
    "market": "NASDAQ",
    "price": 100,
    "prevClose": 99,
    "sharesOutstanding": 1000,
    "color": "#2563EB",
    "about": "ข้อมูลหลักทรัพย์ ROKU - Roku, Inc. Class A Common Stock จดทะเบียนในตลาด NASDAQ สหรัฐอเมริกา ดึงข้อมูลวิเคราะห์เชิงลึกสดเรียลไทม์ด้วย API",
    "revenueHistory": [],
    "fcfHistory": [],
    "priceHistory": [],
    "financials": {
      "revenue": 0,
      "netIncome": 0,
      "eps": 0,
      "bookValuePerShare": 0,
      "freeCashFlow": 0,
      "ebitda": 0,
      "totalDebt": 0,
      "cash": 0,
      "dividendPerShare": 0,
      "growthRate": 0.08
    },
    "assetType": "US_STOCK",
    "currency": "USD"
  },
  {
    "symbol": "ROST",
    "name": "Ross Stores Inc",
    "enName": "Ross Stores Inc",
    "sector": "ค้าปลีก",
    "market": "NASDAQ",
    "price": 100,
    "prevClose": 99,
    "sharesOutstanding": 1000,
    "color": "#2563EB",
    "about": "ข้อมูลหลักทรัพย์ ROST - Ross Stores Inc จดทะเบียนในตลาด NASDAQ สหรัฐอเมริกา ดึงข้อมูลวิเคราะห์เชิงลึกสดเรียลไทม์ด้วย API",
    "revenueHistory": [],
    "fcfHistory": [],
    "priceHistory": [],
    "financials": {
      "revenue": 0,
      "netIncome": 0,
      "eps": 0,
      "bookValuePerShare": 0,
      "freeCashFlow": 0,
      "ebitda": 0,
      "totalDebt": 0,
      "cash": 0,
      "dividendPerShare": 0,
      "growthRate": 0.08
    },
    "assetType": "US_STOCK",
    "currency": "USD"
  },
  {
    "symbol": "RUN",
    "name": "Sunrun Inc",
    "enName": "Sunrun Inc",
    "sector": "เทคโนโลยี",
    "market": "NASDAQ",
    "price": 100,
    "prevClose": 99,
    "sharesOutstanding": 1000,
    "color": "#2563EB",
    "about": "ข้อมูลหลักทรัพย์ RUN - Sunrun Inc จดทะเบียนในตลาด NASDAQ สหรัฐอเมริกา ดึงข้อมูลวิเคราะห์เชิงลึกสดเรียลไทม์ด้วย API",
    "revenueHistory": [],
    "fcfHistory": [],
    "priceHistory": [],
    "financials": {
      "revenue": 0,
      "netIncome": 0,
      "eps": 0,
      "bookValuePerShare": 0,
      "freeCashFlow": 0,
      "ebitda": 0,
      "totalDebt": 0,
      "cash": 0,
      "dividendPerShare": 0,
      "growthRate": 0.08
    },
    "assetType": "US_STOCK",
    "currency": "USD"
  },
  {
    "symbol": "SBUX",
    "name": "Starbucks Corp",
    "enName": "Starbucks Corp",
    "sector": "เทคโนโลยี",
    "market": "NASDAQ",
    "price": 100,
    "prevClose": 99,
    "sharesOutstanding": 1000,
    "color": "#2563EB",
    "about": "ข้อมูลหลักทรัพย์ SBUX - Starbucks Corp จดทะเบียนในตลาด NASDAQ สหรัฐอเมริกา ดึงข้อมูลวิเคราะห์เชิงลึกสดเรียลไทม์ด้วย API",
    "revenueHistory": [],
    "fcfHistory": [],
    "priceHistory": [],
    "financials": {
      "revenue": 0,
      "netIncome": 0,
      "eps": 0,
      "bookValuePerShare": 0,
      "freeCashFlow": 0,
      "ebitda": 0,
      "totalDebt": 0,
      "cash": 0,
      "dividendPerShare": 0,
      "growthRate": 0.08
    },
    "assetType": "US_STOCK",
    "currency": "USD"
  },
  {
    "symbol": "SHY",
    "name": "iShares 1-3 Year Treasury Bond ETF",
    "enName": "iShares 1-3 Year Treasury Bond ETF",
    "sector": "เทคโนโลยี",
    "market": "NASDAQ",
    "price": 100,
    "prevClose": 99,
    "sharesOutstanding": 1000,
    "color": "#2563EB",
    "about": "ข้อมูลหลักทรัพย์ SHY - iShares 1-3 Year Treasury Bond ETF จดทะเบียนในตลาด NASDAQ สหรัฐอเมริกา ดึงข้อมูลวิเคราะห์เชิงลึกสดเรียลไทม์ด้วย API",
    "revenueHistory": [],
    "fcfHistory": [],
    "priceHistory": [],
    "financials": {
      "revenue": 0,
      "netIncome": 0,
      "eps": 0,
      "bookValuePerShare": 0,
      "freeCashFlow": 0,
      "ebitda": 0,
      "totalDebt": 0,
      "cash": 0,
      "dividendPerShare": 0,
      "growthRate": 0.08
    },
    "assetType": "US_STOCK",
    "currency": "USD"
  },
  {
    "symbol": "SNPS",
    "name": "Synopsys Inc",
    "enName": "Synopsys Inc",
    "sector": "เทคโนโลยี",
    "market": "NASDAQ",
    "price": 100,
    "prevClose": 99,
    "sharesOutstanding": 1000,
    "color": "#2563EB",
    "about": "ข้อมูลหลักทรัพย์ SNPS - Synopsys Inc จดทะเบียนในตลาด NASDAQ สหรัฐอเมริกา ดึงข้อมูลวิเคราะห์เชิงลึกสดเรียลไทม์ด้วย API",
    "revenueHistory": [],
    "fcfHistory": [],
    "priceHistory": [],
    "financials": {
      "revenue": 0,
      "netIncome": 0,
      "eps": 0,
      "bookValuePerShare": 0,
      "freeCashFlow": 0,
      "ebitda": 0,
      "totalDebt": 0,
      "cash": 0,
      "dividendPerShare": 0,
      "growthRate": 0.08
    },
    "assetType": "US_STOCK",
    "currency": "USD"
  },
  {
    "symbol": "SOFI",
    "name": "SoFi Technologies, Inc. Common Stock",
    "enName": "SoFi Technologies, Inc. Common Stock",
    "sector": "เทคโนโลยี",
    "market": "NASDAQ",
    "price": 100,
    "prevClose": 99,
    "sharesOutstanding": 1000,
    "color": "#2563EB",
    "about": "ข้อมูลหลักทรัพย์ SOFI - SoFi Technologies, Inc. Common Stock จดทะเบียนในตลาด NASDAQ สหรัฐอเมริกา ดึงข้อมูลวิเคราะห์เชิงลึกสดเรียลไทม์ด้วย API",
    "revenueHistory": [],
    "fcfHistory": [],
    "priceHistory": [],
    "financials": {
      "revenue": 0,
      "netIncome": 0,
      "eps": 0,
      "bookValuePerShare": 0,
      "freeCashFlow": 0,
      "ebitda": 0,
      "totalDebt": 0,
      "cash": 0,
      "dividendPerShare": 0,
      "growthRate": 0.08
    },
    "assetType": "US_STOCK",
    "currency": "USD"
  },
  {
    "symbol": "SOXX",
    "name": "iShares Semiconductor ETF",
    "enName": "iShares Semiconductor ETF",
    "sector": "เทคโนโลยี",
    "market": "NASDAQ",
    "price": 100,
    "prevClose": 99,
    "sharesOutstanding": 1000,
    "color": "#2563EB",
    "about": "ข้อมูลหลักทรัพย์ SOXX - iShares Semiconductor ETF จดทะเบียนในตลาด NASDAQ สหรัฐอเมริกา ดึงข้อมูลวิเคราะห์เชิงลึกสดเรียลไทม์ด้วย API",
    "revenueHistory": [],
    "fcfHistory": [],
    "priceHistory": [],
    "financials": {
      "revenue": 0,
      "netIncome": 0,
      "eps": 0,
      "bookValuePerShare": 0,
      "freeCashFlow": 0,
      "ebitda": 0,
      "totalDebt": 0,
      "cash": 0,
      "dividendPerShare": 0,
      "growthRate": 0.08
    },
    "assetType": "US_STOCK",
    "currency": "USD"
  },
  {
    "symbol": "SPWR",
    "name": "SunPower Inc. Common Stock",
    "enName": "SunPower Inc. Common Stock",
    "sector": "พลังงาน",
    "market": "NASDAQ",
    "price": 100,
    "prevClose": 99,
    "sharesOutstanding": 1000,
    "color": "#2563EB",
    "about": "ข้อมูลหลักทรัพย์ SPWR - SunPower Inc. Common Stock จดทะเบียนในตลาด NASDAQ สหรัฐอเมริกา ดึงข้อมูลวิเคราะห์เชิงลึกสดเรียลไทม์ด้วย API",
    "revenueHistory": [],
    "fcfHistory": [],
    "priceHistory": [],
    "financials": {
      "revenue": 0,
      "netIncome": 0,
      "eps": 0,
      "bookValuePerShare": 0,
      "freeCashFlow": 0,
      "ebitda": 0,
      "totalDebt": 0,
      "cash": 0,
      "dividendPerShare": 0,
      "growthRate": 0.08
    },
    "assetType": "US_STOCK",
    "currency": "USD"
  },
  {
    "symbol": "SQQQ",
    "name": "ProShares UltraPro Short QQQ",
    "enName": "ProShares UltraPro Short QQQ",
    "sector": "เทคโนโลยี",
    "market": "NASDAQ",
    "price": 100,
    "prevClose": 99,
    "sharesOutstanding": 1000,
    "color": "#2563EB",
    "about": "ข้อมูลหลักทรัพย์ SQQQ - ProShares UltraPro Short QQQ จดทะเบียนในตลาด NASDAQ สหรัฐอเมริกา ดึงข้อมูลวิเคราะห์เชิงลึกสดเรียลไทม์ด้วย API",
    "revenueHistory": [],
    "fcfHistory": [],
    "priceHistory": [],
    "financials": {
      "revenue": 0,
      "netIncome": 0,
      "eps": 0,
      "bookValuePerShare": 0,
      "freeCashFlow": 0,
      "ebitda": 0,
      "totalDebt": 0,
      "cash": 0,
      "dividendPerShare": 0,
      "growthRate": 0.08
    },
    "assetType": "US_STOCK",
    "currency": "USD"
  },
  {
    "symbol": "TEAM",
    "name": "Atlassian Corporation Class A Common Stock",
    "enName": "Atlassian Corporation Class A Common Stock",
    "sector": "เทคโนโลยี",
    "market": "NASDAQ",
    "price": 100,
    "prevClose": 99,
    "sharesOutstanding": 1000,
    "color": "#2563EB",
    "about": "ข้อมูลหลักทรัพย์ TEAM - Atlassian Corporation Class A Common Stock จดทะเบียนในตลาด NASDAQ สหรัฐอเมริกา ดึงข้อมูลวิเคราะห์เชิงลึกสดเรียลไทม์ด้วย API",
    "revenueHistory": [],
    "fcfHistory": [],
    "priceHistory": [],
    "financials": {
      "revenue": 0,
      "netIncome": 0,
      "eps": 0,
      "bookValuePerShare": 0,
      "freeCashFlow": 0,
      "ebitda": 0,
      "totalDebt": 0,
      "cash": 0,
      "dividendPerShare": 0,
      "growthRate": 0.08
    },
    "assetType": "US_STOCK",
    "currency": "USD"
  },
  {
    "symbol": "TLT",
    "name": "iShares 20+ Year Treasury Bond ETF",
    "enName": "iShares 20+ Year Treasury Bond ETF",
    "sector": "เทคโนโลยี",
    "market": "NASDAQ",
    "price": 100,
    "prevClose": 99,
    "sharesOutstanding": 1000,
    "color": "#2563EB",
    "about": "ข้อมูลหลักทรัพย์ TLT - iShares 20+ Year Treasury Bond ETF จดทะเบียนในตลาด NASDAQ สหรัฐอเมริกา ดึงข้อมูลวิเคราะห์เชิงลึกสดเรียลไทม์ด้วย API",
    "revenueHistory": [],
    "fcfHistory": [],
    "priceHistory": [],
    "financials": {
      "revenue": 0,
      "netIncome": 0,
      "eps": 0,
      "bookValuePerShare": 0,
      "freeCashFlow": 0,
      "ebitda": 0,
      "totalDebt": 0,
      "cash": 0,
      "dividendPerShare": 0,
      "growthRate": 0.08
    },
    "assetType": "US_STOCK",
    "currency": "USD"
  },
  {
    "symbol": "TQQQ",
    "name": "ProShares  UltraPro QQQ",
    "enName": "ProShares  UltraPro QQQ",
    "sector": "เทคโนโลยี",
    "market": "NASDAQ",
    "price": 100,
    "prevClose": 99,
    "sharesOutstanding": 1000,
    "color": "#2563EB",
    "about": "ข้อมูลหลักทรัพย์ TQQQ - ProShares  UltraPro QQQ จดทะเบียนในตลาด NASDAQ สหรัฐอเมริกา ดึงข้อมูลวิเคราะห์เชิงลึกสดเรียลไทม์ด้วย API",
    "revenueHistory": [],
    "fcfHistory": [],
    "priceHistory": [],
    "financials": {
      "revenue": 0,
      "netIncome": 0,
      "eps": 0,
      "bookValuePerShare": 0,
      "freeCashFlow": 0,
      "ebitda": 0,
      "totalDebt": 0,
      "cash": 0,
      "dividendPerShare": 0,
      "growthRate": 0.08
    },
    "assetType": "US_STOCK",
    "currency": "USD"
  },
  {
    "symbol": "TSLA",
    "name": "Tesla, Inc. Common Stock",
    "enName": "Tesla, Inc. Common Stock",
    "sector": "เทคโนโลยี",
    "market": "NASDAQ",
    "price": 100,
    "prevClose": 99,
    "sharesOutstanding": 1000,
    "color": "#2563EB",
    "about": "ข้อมูลหลักทรัพย์ TSLA - Tesla, Inc. Common Stock จดทะเบียนในตลาด NASDAQ สหรัฐอเมริกา ดึงข้อมูลวิเคราะห์เชิงลึกสดเรียลไทม์ด้วย API",
    "revenueHistory": [],
    "fcfHistory": [],
    "priceHistory": [],
    "financials": {
      "revenue": 0,
      "netIncome": 0,
      "eps": 0,
      "bookValuePerShare": 0,
      "freeCashFlow": 0,
      "ebitda": 0,
      "totalDebt": 0,
      "cash": 0,
      "dividendPerShare": 0,
      "growthRate": 0.08
    },
    "assetType": "US_STOCK",
    "currency": "USD"
  },
  {
    "symbol": "TXN",
    "name": "Texas Instruments Incorporated",
    "enName": "Texas Instruments Incorporated",
    "sector": "เทคโนโลยี",
    "market": "NASDAQ",
    "price": 100,
    "prevClose": 99,
    "sharesOutstanding": 1000,
    "color": "#2563EB",
    "about": "ข้อมูลหลักทรัพย์ TXN - Texas Instruments Incorporated จดทะเบียนในตลาด NASDAQ สหรัฐอเมริกา ดึงข้อมูลวิเคราะห์เชิงลึกสดเรียลไทม์ด้วย API",
    "revenueHistory": [],
    "fcfHistory": [],
    "priceHistory": [],
    "financials": {
      "revenue": 0,
      "netIncome": 0,
      "eps": 0,
      "bookValuePerShare": 0,
      "freeCashFlow": 0,
      "ebitda": 0,
      "totalDebt": 0,
      "cash": 0,
      "dividendPerShare": 0,
      "growthRate": 0.08
    },
    "assetType": "US_STOCK",
    "currency": "USD"
  },
  {
    "symbol": "VRTX",
    "name": "Vertex Pharmaceuticals Inc",
    "enName": "Vertex Pharmaceuticals Inc",
    "sector": "การแพทย์",
    "market": "NASDAQ",
    "price": 100,
    "prevClose": 99,
    "sharesOutstanding": 1000,
    "color": "#2563EB",
    "about": "ข้อมูลหลักทรัพย์ VRTX - Vertex Pharmaceuticals Inc จดทะเบียนในตลาด NASDAQ สหรัฐอเมริกา ดึงข้อมูลวิเคราะห์เชิงลึกสดเรียลไทม์ด้วย API",
    "revenueHistory": [],
    "fcfHistory": [],
    "priceHistory": [],
    "financials": {
      "revenue": 0,
      "netIncome": 0,
      "eps": 0,
      "bookValuePerShare": 0,
      "freeCashFlow": 0,
      "ebitda": 0,
      "totalDebt": 0,
      "cash": 0,
      "dividendPerShare": 0,
      "growthRate": 0.08
    },
    "assetType": "US_STOCK",
    "currency": "USD"
  },
  {
    "symbol": "XEL",
    "name": "Xcel Energy, Inc.",
    "enName": "Xcel Energy, Inc.",
    "sector": "พลังงาน",
    "market": "NASDAQ",
    "price": 100,
    "prevClose": 99,
    "sharesOutstanding": 1000,
    "color": "#2563EB",
    "about": "ข้อมูลหลักทรัพย์ XEL - Xcel Energy, Inc. จดทะเบียนในตลาด NASDAQ สหรัฐอเมริกา ดึงข้อมูลวิเคราะห์เชิงลึกสดเรียลไทม์ด้วย API",
    "revenueHistory": [],
    "fcfHistory": [],
    "priceHistory": [],
    "financials": {
      "revenue": 0,
      "netIncome": 0,
      "eps": 0,
      "bookValuePerShare": 0,
      "freeCashFlow": 0,
      "ebitda": 0,
      "totalDebt": 0,
      "cash": 0,
      "dividendPerShare": 0,
      "growthRate": 0.08
    },
    "assetType": "US_STOCK",
    "currency": "USD"
  },
  {
    "symbol": "ZM",
    "name": "Zoom Communications, Inc. Class A Common Stock",
    "enName": "Zoom Communications, Inc. Class A Common Stock",
    "sector": "เทคโนโลยี",
    "market": "NASDAQ",
    "price": 100,
    "prevClose": 99,
    "sharesOutstanding": 1000,
    "color": "#2563EB",
    "about": "ข้อมูลหลักทรัพย์ ZM - Zoom Communications, Inc. Class A Common Stock จดทะเบียนในตลาด NASDAQ สหรัฐอเมริกา ดึงข้อมูลวิเคราะห์เชิงลึกสดเรียลไทม์ด้วย API",
    "revenueHistory": [],
    "fcfHistory": [],
    "priceHistory": [],
    "financials": {
      "revenue": 0,
      "netIncome": 0,
      "eps": 0,
      "bookValuePerShare": 0,
      "freeCashFlow": 0,
      "ebitda": 0,
      "totalDebt": 0,
      "cash": 0,
      "dividendPerShare": 0,
      "growthRate": 0.08
    },
    "assetType": "US_STOCK",
    "currency": "USD"
  },
  {
    "symbol": "ZS",
    "name": "Zscaler, Inc. Common Stock",
    "enName": "Zscaler, Inc. Common Stock",
    "sector": "เทคโนโลยี",
    "market": "NASDAQ",
    "price": 100,
    "prevClose": 99,
    "sharesOutstanding": 1000,
    "color": "#2563EB",
    "about": "ข้อมูลหลักทรัพย์ ZS - Zscaler, Inc. Common Stock จดทะเบียนในตลาด NASDAQ สหรัฐอเมริกา ดึงข้อมูลวิเคราะห์เชิงลึกสดเรียลไทม์ด้วย API",
    "revenueHistory": [],
    "fcfHistory": [],
    "priceHistory": [],
    "financials": {
      "revenue": 0,
      "netIncome": 0,
      "eps": 0,
      "bookValuePerShare": 0,
      "freeCashFlow": 0,
      "ebitda": 0,
      "totalDebt": 0,
      "cash": 0,
      "dividendPerShare": 0,
      "growthRate": 0.08
    },
    "assetType": "US_STOCK",
    "currency": "USD"
  }
]
